{"weights":{"upper_notes_weight":0.15,"core_notes_weight":0.45,"base_notes_weight":0.4,"characteristics_weight":0.4,"tags_weight":0.5,"overlay_weight":0.1},"runs":[{"input":{"brand":"DIOR","name":"J'adore","sex":"female","image_url":"https://www.letu.ru/common/img/pim/2025/03/EX_eb6096da-5546-4018-887a-422656773396.jpg","properties":{"perfume_type":"eau de parfum","family":["floral"],"upper_notes":["bergamot","ylang-ylang"],"core_notes":["orchid","plum","rose"],"base_notes":["amaranth","jasmine","tobacco"],"upper_tags":["fresh","marine","bright","airy","cool","invigorating","light"],"base_tags":["fruity","romantic","clean","sensual"],"upper_characteristics":{"density":0.15,"earthiness":0.15,"floralcy":0.5,"freshness":0.5,"fruityness":0.15,"powderiness":0.15,"spiciness":0.15,"sweetness":0.15,"warmth":0.15,"woodiness":0.15},"core_characteristics":{"density":0.15,"earthiness":0.15,"floralcy":0.3833333333333333,"freshness":0.15,"fruityness":0.3833333333333333,"powderiness":0.15,"spiciness":0.15,"sweetness":0.15,"warmth":0.15,"woodiness":0.15},"base_characteristics":{"density":0.15,"earthiness":0.15,"floralcy":0.3833333333333333,"freshness":0.15,"fruityness":0.15,"powderiness":0.15,"spiciness":0.15,"sweetness":0.15,"warmth":0.15,"woodiness":0.15}},"shops":[{"shop_name":"Letu","domain":"https://www.letu.ru","variants":[{"volume":30,"link":"https://www.letu.ru/product/dior-j-adore/1114","price":9300}]},{"shop_name":"Gold Apple","domain":"https://goldapple.ru","variants":[{"volume":15,"link":"https://goldapple.ru/7190300064-j-adore","price":28600},{"volume":100,"link":"https://goldapple.ru/7190300009-j-adore","price":18750}]}]},"suggestions":[{"perfume":{"brand":"DIOR","name":"J'аdore Eau de Parfum Roller Pearl","sex":"female","image_url":"https://pcdn.goldapple.ru/p/p/7190300083/imgmain_b741230ae64e4e90ae973c514ef1183f.jpg","properties":{"perfume_type":"eau de parfum","family":["floral"],"upper_notes":["ylang-ylang"],"core_notes":["rose"],"base_notes":["jasmine","tobacco"],"core_tags":["dry","sweet","invigorating","sensual","cozy","energetic","light","calm","rich","warm","caramel","soft","airy","elegant","resinous","clean","mysterious","fruity","romantic","dense"],"base_tags":["energetic","invigorating","mysterious","romantic","sensual","fruity","clean"],"upper_characteristics":{"density":0.15,"earthiness":0.15,"floralcy":0.85,"freshness":0.15,"fruityness":0.15,"powderiness":0.15,"spiciness":0.15,"sweetness":0.15,"warmth":0.15,"woodiness":0.15},"core_characteristics":{"density":0.15,"earthiness":0.15,"floralcy":0.85,"freshness":0.15,"fruityness":0.15,"powderiness":0.15,"spiciness":0.15,"sweetness":0.15,"warmth":0.15,"woodiness":0.15},"base_characteristics":{"density":0.15,"earthiness":0.15,"floralcy":0.5,"freshness":0.15,"fruityness":0.15,"powderiness":0.15,"spiciness":0.15,"sweetness":0.15,"warmth":0.15,"woodiness":0.15}},"shops":[{"shop_name":"Gold Apple","domain":"https://goldapple.ru","variants":[{"volume":20,"link":"https://goldapple.ru/7190300083-j-adore","price":6650}]}]},"rank":1,"similarity_score":0.8404473743165127},{"perfume":{"brand":"Masaki Matsushima","name":"Mat; Limited","sex":"female","image_url":"https://cdn2.randewoo.ru/img/42178/n/1","properties":{"perfume_type":"eau de parfum","family":["floral","fresh"],"upper_notes":["bamboo","mango","pomegranate","tea"],"core_notes":["lotus","osmanthus","rose"],"base_notes":["jasmine","musk","starflower","vodka"],"upper_tags":["energetic","light","soft","fresh","airy","bright","cool"],"base_tags":["dry"],"upper_characteristics":{"density":0.15,"earthiness":0.15,"floralcy":0.15,"freshness":0.15,"fruityness":0.15,"powderiness":0.15,"spiciness":0.15,"sweetness":0.15,"warmth":0.15,"woodiness":0.15},"core_characteristics":{"density":0.15,"earthiness":0.15,"floralcy":0.3833333333333333,"freshness":0.15,"fruityness":0.15,"powderiness":0.15,"spiciness":0.15,"sweetness":0.15,"warmth":0.15,"woodiness":0.15},"base_characteristics":{"density":0.15,"earthiness":0.15,"floralcy":0.5,"freshness":0.15,"fruityness":0.15,"powderiness":0.32499999999999996,"spiciness":0.15,"sweetness":0.15,"warmth":0.15,"woodiness":0.15}},"shops":[{"shop_name":"Gold Apple","domain":"https://goldapple.ru","variants":[{"volume":10,"link":"https://goldapple.ru/19000088219-mat-limited","price":1850}]},{"shop_name":"Randewoo","domain":"https://randewoo.ru","variants":[{"volume":10,"link":"https://randewoo.ru/product/masaki-matsushima-mat-limited?source_category=6\u0026preferred=42178","price":1018},{"volume":40,"link":"https://randewoo.ru/product/masaki-matsushima-mat-limited?source_category=6\u0026preferred=42178","price":3060}]}]},"rank":2,"similarity_score":0.8396128732544853},{"perfume":{"brand":"Burberry","name":"My Burberry Blush","sex":"female","image_url":"https://cdn2.randewoo.ru/img/134613/n/1","properties":{"perfume_type":"eau de parfum","family":["floral"],"upper_notes":["lemon","pomegranate"],"core_notes":["apple","geranium","rose","soybean"],"base_notes":["jasmine","wisteria"],"upper_tags":["light","salty","cool","bright","invigorating","fresh","airy"],"core_tags":["soft","light","dry"],"base_tags":["resinous","elegant","romantic","velvety","sensual","light","dry","cool","calm","airy","fruity","soft","marine","bright","fresh","clean"],"upper_characteristics":{"density":0.15,"earthiness":0.15,"floralcy":0.15,"freshness":0.5,"fruityness":0.15,"powderiness":0.15,"spiciness":0.15,"sweetness":0.15,"warmth":0.15,"woodiness":0.15},"core_characteristics":{"density":0.15,"earthiness":0.15,"floralcy":0.32499999999999996,"freshness":0.15,"fruityness":0.32499999999999996,"powderiness":0.15,"spiciness":0.15,"sweetness":0.15,"warmth":0.15,"woodiness":0.15},"base_characteristics":{"density":0.15,"earthiness":0.15,"floralcy":0.5,"freshness":0.15,"fruityness":0.15,"powderiness":0.15,"spiciness":0.15,"sweetness":0.15,"warmth":0.15,"woodiness":0.15}},"shops":[{"shop_name":"Gold Apple","domain":"https://goldapple.ru","variants":[{"volume":50,"link":"https://goldapple.ru/19000312578-my-burberry-blush","price":12700}]},{"shop_name":"Randewoo","domain":"https://randewoo.ru","variants":[{"volume":50,"link":"https://randewoo.ru/product/burberry-my-burberry-blush?source_category=6\u0026preferred=134613","price":6249},{"volume":90,"link":"https://randewoo.ru/product/burberry-my-burberry-blush?source_category=6\u0026preferred=134613","price":8525},{"volume":8,"link":"https://randewoo.ru/product/burberry-my-burberry-blush?source_category=6\u0026preferred=134613","price":840},{"volume":30,"link":"https://randewoo.ru/product/burberry-my-burberry-blush?source_category=6\u0026preferred=134613","price":5056}]}]},"rank":3,"similarity_score":0.8369659968104866},{"perfume":{"brand":"Xerjoff","name":"More Than Words","sex":"unisex","image_url":"https://cdn2.randewoo.ru/img/19233/n/1","properties":{"perfume_type":"eau de parfum","family":["floral","woody"],"upper_notes":["bergamot"],"core_notes":["heliotrope","rose"],"base_notes":["cyclamen","jasmine"],"upper_tags":["invigorating","light","sharp","fresh","salty","bold","cool","marine","bright","noble","cold","airy"],"base_tags":["velvety","romantic","dry","calm","airy","light","clean","elegant","resinous","sensual","bright","cool","fruity","soft","fresh","marine"],"upper_characteristics":{"density":0.15,"earthiness":0.15,"floralcy":0.15,"freshness":0.85,"fruityness":0.15,"powderiness":0.15,"spiciness":0.15,"sweetness":0.15,"warmth":0.15,"woodiness":0.15},"core_characteristics":{"density":0.15,"earthiness":0.15,"floralcy":0.5,"freshness":0.15,"fruityness":0.15,"powderiness":0.5,"spiciness":0.15,"sweetness":0.15,"warmth":0.15,"woodiness":0.15},"base_characteristics":{"density":0.15,"earthiness":0.15,"floralcy":0.5,"freshness":0.15,"fruityness":0.15,"powderiness":0.15,"spiciness":0.15,"sweetness":0.15,"warmth":0.15,"woodiness":0.15}},"shops":[{"shop_name":"Randewoo","domain":"https://randewoo.ru","variants":[{"volume":100,"link":"https://randewoo.ru/product/xerjoff-join-the-club-more-than-words?source_category=6\u0026preferred=19233","price":16507},{"volume":50,"link":"https://randewoo.ru/product/xerjoff-join-the-club-more-than-words?source_category=6\u0026preferred=19233","price":9448}]}]},"rank":4,"similarity_score":0.8255577824689952}]},{"input":{"brand":"Dolce \u0026 Gabbana","name":"Devotion Eau De Parfum Intense","sex":"female","image_url":"https://cdn2.randewoo.ru/img/496652/n/1","properties":{"perfume_type":"eau de parfum","family":[],"upper_notes":["green forest"],"core_notes":["orange"],"base_notes":["vanilla"],"upper_tags":["light","romantic","dense","airy","energetic","sensual","wet","floral","mossy","rich","resinous","warm"],"core_tags":["romantic","green","sensual","elegant","light","airy","bright","soft","invigorating","bitter","cool","energetic","sweet","powdery","salty","dry","fresh"],"base_tags":["sweet","bitter","cozy","powdery","soft","rich","warm","invigorating","energetic","calm","dry","gourmand","romantic","dense","green","light","mysterious","sensual","velvety","caramel"],"upper_characteristics":{"density":0.15,"earthiness":0.15,"floralcy":0.15,"freshness":0.15,"fruityness":0.15,"powderiness":0.15,"spiciness":0.15,"sweetness":0.15,"warmth":0.15,"woodiness":0.15},"core_characteristics":{"density":0.15,"earthiness":0.15,"floralcy":0.15,"freshness":0.15,"fruityness":0.15,"powderiness":0.15,"spiciness":0.15,"sweetness":0.15,"warmth":0.15,"woodiness":0.15},"base_characteristics":{"density":0.15,"earthiness":0.15,"floralcy":0.15,"freshness":0.15,"fruityness":0.15,"powderiness":0.15,"spiciness":0.15,"sweetness":0.85,"warmth":0.85,"woodiness":0.15}},"shops":[{"shop_name":"Randewoo","domain":"https://randewoo.ru","variants":[{"volume":50,"link":"https://randewoo.ru/product/devotion-eau-de-parfum-intense?source_category=6\u0026preferred=496652","price":6564},{"volume":100,"link":"https://randewoo.ru/product/devotion-eau-de-parfum-intense?source_category=6\u0026preferred=496652","price":8510},{"volume":8,"link":"https://randewoo.ru/product/devotion-eau-de-parfum-intense?source_category=6\u0026preferred=496652","price":945},{"volume":30,"link":"https://randewoo.ru/product/devotion-eau-de-parfum-intense?source_category=6\u0026preferred=496652","price":6130}]}]},"suggestions":[{"perfume":{"brand":"BEAUTIFIC","name":"LONDON REBEL","sex":"female","image_url":"https://pcdn.goldapple.ru/p/p/19000067387/imgmain.jpg","properties":{"perfume_type":"parfum","family":["amber"],"upper_notes":["bohea","cocoa","coffee","tonka beans"],"core_notes":["orange"],"base_notes":["vanilla"],"upper_tags":["warm","romantic","sensual","dry","energetic","cozy","velvety","rich","dense"],"core_tags":["green","sweet","soft","romantic","fresh","invigorating","bright","dry","light","powdery","salty","cool","sensual","elegant","bitter","energetic","airy"],"base_tags":["rich","romantic","caramel","velvety","powdery","calm","light","warm","bitter","dry","energetic","green","mysterious","dense","invigorating","soft","sweet","gourmand","sensual","cozy"],"upper_characteristics":{"density":0.15,"earthiness":0.15,"floralcy":0.15,"freshness":0.15,"fruityness":0.15,"powderiness":0.15,"spiciness":0.15,"sweetness":0.15,"warmth":0.32499999999999996,"woodiness":0.15},"core_characteristics":{"density":0.15,"earthiness":0.15,"floralcy":0.15,"freshness":0.15,"fruityness":0.15,"powderiness":0.15,"spiciness":0.15,"sweetness":0.15,"warmth":0.15,"woodiness":0.15},"base_characteristics":{"density":0.15,"earthiness":0.15,"floralcy":0.15,"freshness":0.15,"fruityness":0.15,"powderiness":0.15,"spiciness":0.15,"sweetness":0.85,"warmth":0.85,"woodiness":0.15}},"shops":[{"shop_name":"Gold Apple","domain":"https://goldapple.ru","variants":[{"volume":10,"link":"https://goldapple.ru/19000067387-london-rebel","price":1144}]}]},"rank":1,"similarity_score":0.866968308470877},{"perfume":{"brand":"Montale","name":"Chocolate Greedy","sex":"unisex","image_url":"https://cdn2.randewoo.ru/img/45376/n/1","properties":{"perfume_type":"eau de parfum","family":["amber"],"upper_notes":["bohea","cocoa","coffee","tonka beans"],"core_notes":["orange"],"base_notes":["vanilla"],"upper_tags":["dry","dense","romantic","energetic","warm","rich","cozy","velvety","sensual"],"core_tags":["light","fresh","invigorating","soft","airy","romantic","dry","green","bitter","elegant","bright","powdery","sweet","energetic","salty","cool","sensual"],"base_tags":["romantic","invigorating","rich","gourmand","sweet","energetic","caramel","bitter","mysterious","green","warm","cozy","soft","velvety","dry","sensual","dense","calm","light","powdery"],"upper_characteristics":{"density":0.15,"earthiness":0.15,"floralcy":0.15,"freshness":0.15,"fruityness":0.15,"powderiness":0.15,"spiciness":0.15,"sweetness":0.15,"warmth":0.32499999999999996,"woodiness":0.15},"core_characteristics":{"density":0.15,"earthiness":0.15,"floralcy":0.15,"freshness":0.15,"fruityness":0.15,"powderiness":0.15,"spiciness":0.15,"sweetness":0.15,"warmth":0.15,"woodiness":0.15},"base_characteristics":{"density":0.15,"earthiness":0.15,"floralcy":0.15,"freshness":0.15,"fruityness":0.15,"powderiness":0.15,"spiciness":0.15,"sweetness":0.85,"warmth":0.85,"woodiness":0.15}},"shops":[{"shop_name":"Gold Apple","domain":"https://goldapple.ru","variants":[{"volume":50,"link":"https://goldapple.ru/26163500002-chocolate-greedy","price":12500}]},{"shop_name":"Randewoo","domain":"https://randewoo.ru","variants":[{"volume":50,"link":"https://randewoo.ru/product/montale-chocolate-greedy?source_category=6\u0026preferred=45376","price":5322},{"volume":8,"link":"https://randewoo.ru/product/montale-chocolate-greedy?source_category=6\u0026preferred=45376","price":745},{"volume":20,"link":"https://randewoo.ru/product/montale-chocolate-greedy?source_category=6\u0026preferred=45376","price":5326},{"volume":100,"link":"https://randewoo.ru/product/montale-chocolate-greedy?source_category=6\u0026preferred=45376","price":7217}]}]},"rank":2,"similarity_score":0.866968308470877},{"perfume":{"brand":"Ghost","name":"Orb Of Night Elixir","sex":"female","image_url":"https://cdn2.randewoo.ru/img/532569/n/1","properties":{"perfume_type":"parfum","family":[],"upper_notes":["cherry"],"core_notes":["orange"],"base_notes":["vanilla"],"upper_tags":["sensual","fresh","bitter","romantic","powdery","soft","bright","light","energetic","cool","sweet","green","dry","elegant"],"core_tags":["bitter","elegant","dry","sweet","invigorating","romantic","soft","bright","energetic","fresh","airy","powdery","salty","sensual","green","light","cool"],"base_tags":["mysterious","sensual","cozy","bitter","green","soft","energetic","sweet","calm","powdery","romantic","invigorating","warm","dense","caramel","dry","velvety","gourmand","light","rich"],"upper_characteristics":{"density":0.15,"earthiness":0.15,"floralcy":0.15,"freshness":0.15,"fruityness":0.15,"powderiness":0.15,"spiciness":0.15,"sweetness":0.15,"warmth":0.15,"woodiness":0.15},"core_characteristics":{"density":0.15,"earthiness":0.15,"floralcy":0.15,"freshness":0.15,"fruityness":0.15,"powderiness":0.15,"spiciness":0.15,"sweetness":0.15,"warmth":0.15,"woodiness":0.15},"base_characteristics":{"density":0.15,"earthiness":0.15,"floralcy":0.15,"freshness":0.15,"fruityness":0.15,"powderiness":0.15,"spiciness":0.15,"sweetness":0.85,"warmth":0.85,"woodiness":0.15}},"shops":[{"shop_name":"Randewoo","domain":"https://randewoo.ru","variants":[{"volume":75,"link":"https://randewoo.ru/product/orb-of-night-elixir?source_category=6\u0026preferred=532569","price":0}]}]},"rank":3,"similarity_score":0.8481455024943139},{"perfume":{"brand":"Miu Miu","name":"Les Eaux A La Mode - Serial Player","sex":"female","image_url":"https://cdn2.randewoo.ru/img/382384/n/1","properties":{"perfume_type":"eau de toilette","family":[],"upper_notes":["litchi"],"core_notes":["orange"],"base_notes":["vanilla"],"upper_tags":["cool","light","fresh","soft","powdery","dry","green","sweet","invigorating","elegant","bright","salty","romantic","bitter","sensual","energetic"],"core_tags":["airy","cool","fresh","sweet","elegant","green","salty","bitter","sensual","romantic","light","dry","bright","powdery","invigorating","energetic","soft"],"base_tags":["light","rich","warm","invigorating","gourmand","powdery","cozy","dry","dense","energetic","romantic","velvety","sensual","green","caramel","calm","sweet","soft","bitter","mysterious"],"upper_characteristics":{"density":0.15,"earthiness":0.15,"floralcy":0.15,"freshness":0.15,"fruityness":0.15,"powderiness":0.15,"spiciness":0.15,"sweetness":0.15,"warmth":0.15,"woodiness":0.15},"core_characteristics":{"density":0.15,"earthiness":0.15,"floralcy":0.15,"freshness":0.15,"fruityness":0.15,"powderiness":0.15,"spiciness":0.15,"sweetness":0.15,"warmth":0.15,"woodiness":0.15},"base_characteristics":{"density":0.15,"earthiness":0.15,"floralcy":0.15,"freshness":0.15,"fruityness":0.15,"powderiness":0.15,"spiciness":0.15,"sweetness":0.85,"warmth":0.85,"woodiness":0.15}},"shops":[{"shop_name":"Randewoo","domain":"https://randewoo.ru","variants":[{"volume":50,"link":"https://randewoo.ru/product/les-eaux-a-la-mode-serial-player?source_category=6\u0026preferred=382384","price":5859}]}]},"rank":4,"similarity_score":0.846650635094611}]},{"input":{"brand":"Dolce \u0026 Gabbana","name":"Dolce Lily","sex":"female","image_url":"https://cdn2.randewoo.ru/img/402925/n/1","properties":{"perfume_type":"eau de toilette","family":[],"upper_notes":["bergamot","passionfruit"],"core_notes":["lily","rose"],"base_notes":["musk","sandalwood","vanilla"],"upper_tags":["bright","airy","salty","cool","light","fresh","invigorating"],"base_tags":["cozy","rich","energetic","soft","dense","warm","mysterious","sensual","romantic"],"upper_characteristics":{"density":0.15,"earthiness":0.15,"floralcy":0.15,"freshness":0.5,"fruityness":0.5,"powderiness":0.15,"spiciness":0.15,"sweetness":0.15,"warmth":0.15,"woodiness":0.15},"core_characteristics":{"density":0.15,"earthiness":0.15,"floralcy":0.85,"freshness":0.15,"fruityness":0.15,"powderiness":0.15,"spiciness":0.15,"sweetness":0.15,"warmth":0.15,"woodiness":0.15},"base_characteristics":{"density":0.15,"earthiness":0.15,"floralcy":0.15,"freshness":0.15,"fruityness":0.15,"powderiness":0.3833333333333333,"spiciness":0.15,"sweetness":0.3833333333333333,"warmth":0.3833333333333333,"woodiness":0.3833333333333333}},"shops":[{"shop_name":"Randewoo","domain":"https://randewoo.ru","variants":[{"volume":8,"link":"https://randewoo.ru/product/dolce-lily?source_category=6\u0026preferred=402925","price":645},{"volume":50,"link":"https://randewoo.ru/product/dolce-lily?source_category=6\u0026preferred=402925","price":3241},{"volume":5,"link":"https://randewoo.ru/product/dolce-lily?source_category=6\u0026preferred=402925","price":1391},{"volume":75,"link":"https://randewoo.ru/product/dolce-lily?source_category=6\u0026preferred=402925","price":6068}]}]},"suggestions":[{"perfume":{"brand":"Dolce \u0026 Gabbana","name":"Dolce Lily Eau de Toilette","sex":"female","image_url":"https://pcdn.goldapple.ru/p/p/19000039297/imgmain.jpg","properties":{"perfume_type":"eau de toilette","family":["floral"],"upper_notes":["bergamot","passionfruit"],"core_notes":["lily","peony","rose"],"base_notes":["musk","sandalwood","vanilla"],"upper_tags":["fresh","invigorating","airy","salty","cool","light","bright"],"core_tags":["dry","energetic","soft","elegant","romantic","calm","airy","resinous","invigorating","light","clean","fruity","sensual"],"base_tags":["cozy","dense","sensual","warm","romantic","rich","soft","mysterious","energetic"],"upper_characteristics":{"density":0.15,"earthiness":0.15,"floralcy":0.15,"freshness":0.5,"fruityness":0.5,"powderiness":0.15,"spiciness":0.15,"sweetness":0.15,"warmth":0.15,"woodiness":0.15},"core_characteristics":{"density":0.15,"earthiness":0.15,"floralcy":0.6166666666666667,"freshness":0.15,"fruityness":0.15,"powderiness":0.15,"spiciness":0.15,"sweetness":0.15,"warmth":0.15,"woodiness":0.15},"base_characteristics":{"density":0.15,"earthiness":0.15,"floralcy":0.15,"freshness":0.15,"fruityness":0.15,"powderiness":0.3833333333333333,"spiciness":0.15,"sweetness":0.3833333333333333,"warmth":0.3833333333333333,"woodiness":0.3833333333333333}},"shops":[{"shop_name":"Gold Apple","domain":"https://goldapple.ru","variants":[{"volume":75,"link":"https://goldapple.ru/19000039297-dolce-lily-eau-de-toilette","price":14800}]}]},"rank":1,"similarity_score":0.891393526082707},{"perfume":{"brand":"WIDIAN AJ Arabia","name":"IV","sex":"unisex","image_url":"https://cdn2.randewoo.ru/img/22949/n/1","properties":{"perfume_type":"parfum","family":["amber"],"upper_notes":["bergamot","black currant","plum"],"core_notes":["rose"],"base_notes":["musk","sandalwood","skin","vanilla"],"upper_tags":["salty","invigorating","light"],"core_tags":["sweet","invigorating","energetic","dry","fruity","airy","resinous","rich","caramel","cozy","soft","calm","light","mysterious","elegant","sensual","dense","romantic","clean","warm"],"base_tags":["dense","warm","soft","rich"],"upper_characteristics":{"density":0.15,"earthiness":0.15,"floralcy":0.15,"freshness":0.3833333333333333,"fruityness":0.3833333333333333,"powderiness":0.15,"spiciness":0.15,"sweetness":0.15,"warmth":0.15,"woodiness":0.15},"core_characteristics":{"density":0.15,"earthiness":0.15,"floralcy":0.85,"freshness":0.15,"fruityness":0.15,"powderiness":0.15,"spiciness":0.15,"sweetness":0.15,"warmth":0.15,"woodiness":0.15},"base_characteristics":{"density":0.15,"earthiness":0.15,"floralcy":0.15,"freshness":0.15,"fruityness":0.15,"powderiness":0.32499999999999996,"spiciness":0.15,"sweetness":0.32499999999999996,"warmth":0.32499999999999996,"woodiness":0.32499999999999996}},"shops":[{"shop_name":"Randewoo","domain":"https://randewoo.ru","variants":[{"volume":50,"link":"https://randewoo.ru/product/widian-aj-arabia-iv?source_category=6\u0026preferred=22949","price":20736}]}]},"rank":2,"similarity_score":0.8876503396161867},{"perfume":{"brand":"Jacomo","name":"Le Parfum","sex":"female","image_url":"https://cdn2.randewoo.ru/img/12480/n/1","properties":{"perfume_type":"eau de parfum","family":["amber","floral","fresh"],"upper_notes":["bergamot","peach","tangerine"],"core_notes":["jasmine","rose"],"base_notes":["musk","sandalwood","vanilla"],"upper_tags":["cool","fresh","airy","invigorating","salty","bright","light"],"core_tags":["resinous","energetic","romantic","soft","light","mysterious","invigorating","calm","dry","clean","elegant","airy","fruity","sensual"],"base_tags":["warm","romantic","sensual","mysterious","dense","energetic","soft","cozy","rich"],"upper_characteristics":{"density":0.15,"earthiness":0.15,"floralcy":0.15,"freshness":0.3833333333333333,"fruityness":0.3833333333333333,"powderiness":0.15,"spiciness":0.15,"sweetness":0.15,"warmth":0.15,"woodiness":0.15},"core_characteristics":{"density":0.15,"earthiness":0.15,"floralcy":0.85,"freshness":0.15,"fruityness":0.15,"powderiness":0.15,"spiciness":0.15,"sweetness":0.15,"warmth":0.15,"woodiness":0.15},"base_characteristics":{"density":0.15,"earthiness":0.15,"floralcy":0.15,"freshness":0.15,"fruityness":0.15,"powderiness":0.3833333333333333,"spiciness":0.15,"sweetness":0.3833333333333333,"warmth":0.3833333333333333,"woodiness":0.3833333333333333}},"shops":[{"shop_name":"Randewoo","domain":"https://randewoo.ru","variants":[{"volume":100,"link":"https://randewoo.ru/product/jacomo-le-parfum?source_category=6\u0026preferred=12480","price":6324}]}]},"rank":3,"similarity_score":0.8836620770809638},{"perfume":{"brand":"Rania J","name":"Rose Ishtar","sex":"female","image_url":"https://cdn2.randewoo.ru/img/35118/n/1","properties":{"perfume_type":"eau de parfum","family":["amber","floral"],"upper_notes":["bergamot","black currant"],"core_notes":["rose"],"base_notes":["heliotrope","musk","patchouli","sandalwood","vanilla"],"upper_tags":["light","cool","bright","salty","fresh","invigorating","airy"],"core_tags":["resinous","dry","elegant","rich","light","invigorating","dense","mysterious","soft","warm","cozy","calm","sweet","caramel","sensual","airy","clean","romantic","energetic","fruity"],"base_tags":["mysterious","rich","energetic","romantic","sensual","dense","warm"],"upper_characteristics":{"density":0.15,"earthiness":0.15,"floralcy":0.15,"freshness":0.5,"fruityness":0.15,"powderiness":0.15,"spiciness":0.15,"sweetness":0.15,"warmth":0.15,"woodiness":0.15},"core_characteristics":{"density":0.15,"earthiness":0.15,"floralcy":0.85,"freshness":0.15,"fruityness":0.15,"powderiness":0.15,"spiciness":0.15,"sweetness":0.15,"warmth":0.15,"woodiness":0.15},"base_characteristics":{"density":0.15,"earthiness":0.2899999999999999,"floralcy":0.15,"freshness":0.15,"fruityness":0.15,"powderiness":0.43,"spiciness":0.15,"sweetness":0.29,"warmth":0.29,"woodiness":0.2899999999999999}},"shops":[{"shop_name":"Randewoo","domain":"https://randewoo.ru","variants":[{"volume":50,"link":"https://randewoo.ru/product/rania-j-rose-ishtar?source_category=6\u0026preferred=35118","price":7010}]}]},"rank":4,"similarity_score":0.8827912329352434}]},{"input":{"brand":"1907","name":"Cedar Blue","sex":"male","image_url":"https://cdn2.randewoo.ru/img/440180/n/1","properties":{"perfume_type":"eau de parfum","family":["fresh","woody"],"upper_notes":["bergamot","grapefruit","lemon","mint","tangerine","thyme"],"core_notes":["aquatic notes","melon"],"base_notes":["amber","cedar","oakmoss","patchouli","sandalwood"],"upper_tags":["salty","noble","invigorating","fresh","bold","airy","light","cold","bright","sharp","cool","marine"],"core_tags":["fresh","bright","cool","light","airy"],"base_tags":["floral","rich","mysterious","warm","mossy","earthy","dense","energetic"],"upper_characteristics":{"density":0.15,"earthiness":0.15,"floralcy":0.15,"freshness":0.5,"fruityness":0.2666666666666666,"powderiness":0.15,"spiciness":0.15,"sweetness":0.15,"warmth":0.15,"woodiness":0.15},"core_characteristics":{"density":0.15,"earthiness":0.15,"floralcy":0.15,"freshness":0.15,"fruityness":0.15,"powderiness":0.15,"spiciness":0.15,"sweetness":0.15,"warmth":0.15,"woodiness":0.15},"base_characteristics":{"density":0.2899999999999999,"earthiness":0.43,"floralcy":0.15,"freshness":0.15,"fruityness":0.15,"powderiness":0.15,"spiciness":0.15,"sweetness":0.15,"warmth":0.2899999999999999,"woodiness":0.5700000000000001}},"shops":[{"shop_name":"Randewoo","domain":"https://randewoo.ru","variants":[{"volume":100,"link":"https://randewoo.ru/product/cedar-blue?source_category=6\u0026preferred=440180","price":15920}]}]},"suggestions":[{"perfume":{"brand":"Yves Saint Laurent","name":"L'Homme Cologne Bleue","sex":"male","image_url":"https://cdn2.randewoo.ru/img/185430/n/1","properties":{"perfume_type":"eau de toilette","family":[],"upper_notes":["bergamot","cardamom","grapefruit","tangerine"],"core_notes":["apple","aquatic notes","geranium","lavender","thyme"],"base_notes":["cedar","patchouli","sandalwood"],"upper_tags":["marine","light","bright","cool","fresh","salty","airy","sharp","invigorating"],"core_tags":["airy","cool","fresh","light","bright","elegant"],"base_tags":["warm","earthy","floral","rich","energetic","mossy","dense","mysterious"],"upper_characteristics":{"density":0.15,"earthiness":0.15,"floralcy":0.15,"freshness":0.32499999999999996,"fruityness":0.32499999999999996,"powderiness":0.15,"spiciness":0.32499999999999996,"sweetness":0.15,"warmth":0.15,"woodiness":0.15},"core_characteristics":{"density":0.15,"earthiness":0.15,"floralcy":0.15,"freshness":0.15,"fruityness":0.2899999999999999,"powderiness":0.15,"spiciness":0.15,"sweetness":0.15,"warmth":0.15,"woodiness":0.15},"base_characteristics":{"density":0.15,"earthiness":0.3833333333333333,"floralcy":0.15,"freshness":0.15,"fruityness":0.15,"powderiness":0.15,"spiciness":0.15,"sweetness":0.15,"warmth":0.15,"woodiness":0.6166666666666667}},"shops":[{"shop_name":"Randewoo","domain":"https://randewoo.ru","variants":[{"volume":100,"link":"https://randewoo.ru/product/yves-saint-laurent-l-homme-cologne-bleue?source_category=6\u0026preferred=185430","price":12118}]}]},"rank":1,"similarity_score":0.8571858443104083},{"perfume":{"brand":"Gucci","name":"Guilty Pour Homme Platinum","sex":"male","image_url":"https://cdn2.randewoo.ru/img/91340/n/1","properties":{"perfume_type":"eau de toilette","family":["fresh","woody"],"upper_notes":["lavender","lemon"],"core_notes":["orange"],"base_notes":["cedar","patchouli"],"upper_tags":["cool","light","sharp","marine","bright","fresh","airy"],"core_tags":["fresh","elegant","bright","dry","romantic","cool","energetic","green","powdery","soft","airy","invigorating","bitter","sweet","sensual","salty","light"],"base_tags":["mossy","mysterious","floral","dense","energetic","warm","earthy","rich"],"upper_characteristics":{"density":0.15,"earthiness":0.15,"floralcy":0.15,"freshness":0.5,"fruityness":0.15,"powderiness":0.15,"spiciness":0.15,"sweetness":0.15,"warmth":0.15,"woodiness":0.15},"core_characteristics":{"density":0.15,"earthiness":0.15,"floralcy":0.15,"freshness":0.15,"fruityness":0.15,"powderiness":0.15,"spiciness":0.15,"sweetness":0.15,"warmth":0.15,"woodiness":0.15},"base_characteristics":{"density":0.15,"earthiness":0.5,"floralcy":0.15,"freshness":0.15,"fruityness":0.15,"powderiness":0.15,"spiciness":0.15,"sweetness":0.15,"warmth":0.15,"woodiness":0.5}},"shops":[{"shop_name":"Randewoo","domain":"https://randewoo.ru","variants":[{"volume":90,"link":"https://randewoo.ru/product/gucci-guilty-pour-homme-platinum?source_category=6\u0026preferred=91340","price":25364}]}]},"rank":2,"similarity_score":0.8523604240903389},{"perfume":{"brand":"Jul et Mad Paris","name":"Aqua Sextius","sex":"unisex","image_url":"https://cdn2.randewoo.ru/img/10960/n/1","properties":{"perfume_type":"parfum","family":["fresh"],"upper_notes":["bergamot","grapefruit","lemon","orange"],"core_notes":["aquatic notes","eucalyptus","fig","mimosa","mint"],"base_notes":["amber","cedar","guaiac","incienso","musk","oakmoss"],"upper_tags":["bright","salty","bold","airy","noble","invigorating","marine","light","cold","cool","sharp","fresh"],"core_tags":["airy","invigorating","light"],"base_tags":["rich","dense","floral","mysterious","warm","mossy","energetic","earthy"],"upper_characteristics":{"density":0.15,"earthiness":0.15,"floralcy":0.15,"freshness":0.5,"fruityness":0.32499999999999996,"powderiness":0.15,"spiciness":0.15,"sweetness":0.15,"warmth":0.15,"woodiness":0.15},"core_characteristics":{"density":0.15,"earthiness":0.15,"floralcy":0.15,"freshness":0.29,"fruityness":0.15,"powderiness":0.15,"spiciness":0.15,"sweetness":0.15,"warmth":0.15,"woodiness":0.15},"base_characteristics":{"density":0.2666666666666666,"earthiness":0.26666666666666666,"floralcy":0.15,"freshness":0.15,"fruityness":0.15,"powderiness":0.26666666666666666,"spiciness":0.15,"sweetness":0.15,"warmth":0.2666666666666666,"woodiness":0.5}},"shops":[{"shop_name":"Randewoo","domain":"https://randewoo.ru","variants":[{"volume":50,"link":"https://randewoo.ru/product/jul-et-mad-paris-aqua-sextius?source_category=6\u0026preferred=10960","price":22240}]}]},"rank":3,"similarity_score":0.8475713929803335},{"perfume":{"brand":"El Ganso","name":"Like Father Like Son","sex":"male","image_url":"https://pcdn.goldapple.ru/p/p/19000325813/imgmain_ef0517f457cf4df7b72189a7d4e69582.jpeg","properties":{"perfume_type":"eau de toilette","family":["fresh"],"upper_notes":["ginger","grapefruit","lemon"],"core_notes":["floral","mint","orange","pear"],"base_notes":["amber","sandalwood","vetiver"],"upper_tags":["bright","salty","sharp","cool","bold","cold","noble","marine","fresh","light","invigorating","airy"],"core_tags":["airy","light","bright","cool","fresh","invigorating"],"base_tags":["earthy","warm","mossy","rich","dense","energetic","mysterious","floral"],"upper_characteristics":{"density":0.15,"earthiness":0.15,"floralcy":0.15,"freshness":0.3833333333333333,"fruityness":0.3833333333333333,"powderiness":0.15,"spiciness":0.3833333333333333,"sweetness":0.15,"warmth":0.15,"woodiness":0.15},"core_characteristics":{"density":0.15,"earthiness":0.15,"floralcy":0.15,"freshness":0.32499999999999996,"fruityness":0.32499999999999996,"powderiness":0.15,"spiciness":0.15,"sweetness":0.15,"warmth":0.15,"woodiness":0.15},"base_characteristics":{"density":0.3833333333333333,"earthiness":0.3833333333333333,"floralcy":0.15,"freshness":0.15,"fruityness":0.15,"powderiness":0.15,"spiciness":0.15,"sweetness":0.15,"warmth":0.3833333333333333,"woodiness":0.3833333333333333}},"shops":[{"shop_name":"Gold Apple","domain":"https://goldapple.ru","variants":[{"volume":75,"link":"https://goldapple.ru/19000325813-like-father-like-son","price":5680}]}]},"rank":4,"similarity_score":0.8448479810048343}]},{"input":{"brand":"Abercrombie \u0026 Fitch","name":"Authentic Self Man","sex":"male","image_url":"https://cdn2.randewoo.ru/img/443688/n/1","properties":{"perfume_type":"eau de toilette","family":[],"upper_notes":["cardamom","cypress","ginger"],"core_notes":["geranium"],"base_notes":["cedar","vanilla"],"upper_tags":["dense","clean","sharp","rich","resinous","vanillic","marine","bright","floral","energetic","mossy"],"core_tags":["calm","fruity","bright","airy","fresh","romantic","marine","light","sensual","velvety","elegant","dry","soft","clean","resinous","cool"],"base_tags":["rich","warm","dense","energetic","calm","mysterious"],"upper_characteristics":{"density":0.15,"earthiness":0.15,"floralcy":0.15,"freshness":0.15,"fruityness":0.15,"powderiness":0.15,"spiciness":0.6166666666666667,"sweetness":0.15,"warmth":0.15,"woodiness":0.15},"core_characteristics":{"density":0.15,"earthiness":0.15,"floralcy":0.15,"freshness":0.15,"fruityness":0.15,"powderiness":0.15,"spiciness":0.15,"sweetness":0.15,"warmth":0.15,"woodiness":0.15},"base_characteristics":{"density":0.15,"earthiness":0.15,"floralcy":0.15,"freshness":0.15,"fruityness":0.15,"powderiness":0.15,"spiciness":0.15,"sweetness":0.5,"warmth":0.5,"woodiness":0.5}},"shops":[{"shop_name":"Randewoo","domain":"https://randewoo.ru","variants":[{"volume":30,"link":"https://randewoo.ru/product/authentic-self-man?source_category=6\u0026preferred=443688","price":4091}]}]},"suggestions":[{"perfume":{"brand":"Roberto Cavalli","name":"Imperial Hyacinth","sex":"unisex","image_url":"https://cdn2.randewoo.ru/img/193040/n/1","properties":{"perfume_type":"eau de parfum","family":["amber","floral"],"upper_notes":["bergamot","cardamom","saffron"],"core_notes":["hyacinth","petalia"],"base_notes":["cedar","musk","vanilla"],"upper_tags":["energetic","mossy","sharp","marine","resinous","bright","dense","vanillic","clean","rich","floral"],"core_tags":["invigorating","clean","fresh","soft","calm","dry","sensual","marine","romantic","resinous","energetic","fruity","airy","light","elegant","cool","velvety","bright"],"base_tags":["dense","energetic","mysterious","warm","rich"],"upper_characteristics":{"density":0.15,"earthiness":0.15,"floralcy":0.15,"freshness":0.3833333333333333,"fruityness":0.15,"powderiness":0.15,"spiciness":0.3833333333333333,"sweetness":0.15,"warmth":0.15,"woodiness":0.15},"core_characteristics":{"density":0.15,"earthiness":0.15,"floralcy":0.15,"freshness":0.15,"fruityness":0.15,"powderiness":0.15,"spiciness":0.15,"sweetness":0.15,"warmth":0.15,"woodiness":0.15},"base_characteristics":{"density":0.15,"earthiness":0.15,"floralcy":0.15,"freshness":0.15,"fruityness":0.15,"powderiness":0.3833333333333333,"spiciness":0.15,"sweetness":0.3833333333333333,"warmth":0.3833333333333333,"woodiness":0.3833333333333333}},"shops":[{"shop_name":"Randewoo","domain":"https://randewoo.ru","variants":[{"volume":100,"link":"https://randewoo.ru/product/roberto-cavalli-imperial-hyacinth?source_category=6\u0026preferred=193040","price":11636}]}]},"rank":1,"similarity_score":0.851407307898419},{"perfume":{"brand":"Laura Biagiotti","name":"Roma Uomo","sex":"male","image_url":"https://cdn2.randewoo.ru/img/12715/n/1","properties":{"perfume_type":"eau de toilette","family":["fresh","woody"],"upper_notes":["bay"],"core_notes":["geranium"],"base_notes":["coumarin","vanilla"],"upper_tags":["resinous","energetic","marine","vanillic","clean","bright","sharp","dense","rich","floral","mossy"],"core_tags":["fruity","airy","resinous","romantic","sensual","elegant","cool","velvety","dry","fresh","light","bright","calm","clean","soft","marine"],"base_tags":["dense","energetic","mysterious","velvety","sensual","powdery","rich","sweet","light","romantic","soft","warm","cozy","caramel","dry"],"upper_characteristics":{"density":0.15,"earthiness":0.15,"floralcy":0.15,"freshness":0.15,"fruityness":0.15,"powderiness":0.15,"spiciness":0.15,"sweetness":0.15,"warmth":0.15,"woodiness":0.15},"core_characteristics":{"density":0.15,"earthiness":0.15,"floralcy":0.15,"freshness":0.15,"fruityness":0.15,"powderiness":0.15,"spiciness":0.15,"sweetness":0.15,"warmth":0.15,"woodiness":0.15},"base_characteristics":{"density":0.15,"earthiness":0.15,"floralcy":0.15,"freshness":0.15,"fruityness":0.15,"powderiness":0.15,"spiciness":0.15,"sweetness":0.5,"warmth":0.5,"woodiness":0.15}},"shops":[{"shop_name":"Randewoo","domain":"https://randewoo.ru","variants":[{"volume":75,"link":"https://randewoo.ru/product/laura-biagiotti-roma-uomo?source_category=6\u0026preferred=12715","price":5780}]}]},"rank":2,"similarity_score":0.8510563512295097},{"perfume":{"brand":"Laura Biagiotti","name":"Essenza Di Roma Uomo","sex":"male","image_url":"https://cdn2.randewoo.ru/img/46206/n/1","properties":{"perfume_type":"eau de toilette","family":["fresh","woody"],"upper_notes":["bay"],"core_notes":["geranium"],"base_notes":["coumarin","vanilla"],"upper_tags":["sharp","clean","marine","floral","mossy","rich","dense","bright","energetic","resinous","vanillic"],"core_tags":["dry","velvety","fresh","cool","sensual","romantic","soft","clean","marine","bright","light","fruity","airy","elegant","resinous","calm"],"base_tags":["sweet","powdery","cozy","dry","romantic","warm","dense","energetic","light","velvety","soft","caramel","mysterious","rich","sensual"],"upper_characteristics":{"density":0.15,"earthiness":0.15,"floralcy":0.15,"freshness":0.15,"fruityness":0.15,"powderiness":0.15,"spiciness":0.15,"sweetness":0.15,"warmth":0.15,"woodiness":0.15},"core_characteristics":{"density":0.15,"earthiness":0.15,"floralcy":0.15,"freshness":0.15,"fruityness":0.15,"powderiness":0.15,"spiciness":0.15,"sweetness":0.15,"warmth":0.15,"woodiness":0.15},"base_characteristics":{"density":0.15,"earthiness":0.15,"floralcy":0.15,"freshness":0.15,"fruityness":0.15,"powderiness":0.15,"spiciness":0.15,"sweetness":0.5,"warmth":0.5,"woodiness":0.15}},"shops":[{"shop_name":"Randewoo","domain":"https://randewoo.ru","variants":[{"volume":125,"link":"https://randewoo.ru/product/laura-biagiotti-essenza-di-roma-uomo?source_category=6\u0026preferred=46206","price":12262}]}]},"rank":3,"similarity_score":0.8510563512295097},{"perfume":{"brand":"Asgharali","name":"Step Up","sex":"unisex","image_url":"https://cdn2.randewoo.ru/img/254842/n/1","properties":{"perfume_type":"eau de parfum","family":["amber","fresh"],"upper_notes":["bergamot","cinnamon","pepper"],"core_notes":["geranium"],"base_notes":["amber","musk","vanilla"],"upper_tags":["marine","bright","vanillic","fresh","cold","rich","sharp","dense","energetic"],"core_tags":["light","clean","elegant","airy","velvety","sensual","resinous","dry","bright","fresh","cool","fruity","calm","romantic","soft","marine"],"base_tags":["warm","energetic","dense","rich","cozy","mysterious","dry"],"upper_characteristics":{"density":0.15,"earthiness":0.15,"floralcy":0.15,"freshness":0.3833333333333333,"fruityness":0.15,"powderiness":0.15,"spiciness":0.6166666666666667,"sweetness":0.15,"warmth":0.15,"woodiness":0.15},"core_characteristics":{"density":0.15,"earthiness":0.15,"floralcy":0.15,"freshness":0.15,"fruityness":0.15,"powderiness":0.15,"spiciness":0.15,"sweetness":0.15,"warmth":0.15,"woodiness":0.15},"base_characteristics":{"density":0.3833333333333333,"earthiness":0.15,"floralcy":0.15,"freshness":0.15,"fruityness":0.15,"powderiness":0.3833333333333333,"spiciness":0.15,"sweetness":0.3833333333333333,"warmth":0.6166666666666667,"woodiness":0.15}},"shops":[{"shop_name":"Randewoo","domain":"https://randewoo.ru","variants":[{"volume":50,"link":"https://randewoo.ru/product/asgharali-step-up?source_category=6\u0026preferred=254842","price":0}]}]},"rank":4,"similarity_score":0.8415860846867103}]},{"input":{"brand":"Adidas","name":"UEFA Champions League Champions Intense","sex":"male","image_url":"https://cdn2.randewoo.ru/img/426918/n/1","properties":{"perfume_type":"eau de parfum","family":["fresh"],"upper_notes":["lavender","lemon"],"core_notes":["apple"],"base_notes":["moss","patchouli","vanilla"],"upper_tags":["fresh","marine","light","airy","cool","sharp","bright"],"core_tags":["bright","soft","elegant","sensual","sweet","light","cool","invigorating","bitter","dry","fresh","salty","romantic","energetic","powdery","green","airy"],"base_tags":["energetic","mysterious","invigorating","mossy","warm","romantic","sensual","dense","rich"],"upper_characteristics":{"density":0.15,"earthiness":0.15,"floralcy":0.15,"freshness":0.5,"fruityness":0.15,"powderiness":0.15,"spiciness":0.15,"sweetness":0.15,"warmth":0.15,"woodiness":0.15},"core_characteristics":{"density":0.15,"earthiness":0.15,"floralcy":0.15,"freshness":0.15,"fruityness":0.85,"powderiness":0.15,"spiciness":0.15,"sweetness":0.15,"warmth":0.15,"woodiness":0.15},"base_characteristics":{"density":0.15,"earthiness":0.6166666666666666,"floralcy":0.15,"freshness":0.15,"fruityness":0.15,"powderiness":0.15,"spiciness":0.15,"sweetness":0.3833333333333333,"warmth":0.3833333333333333,"woodiness":0.15}},"shops":[{"shop_name":"Randewoo","domain":"https://randewoo.ru","variants":[{"volume":100,"link":"https://randewoo.ru/product/uefa-champions-league-champions-intense?source_category=6\u0026preferred=426918","price":0}]}]},"suggestions":[{"perfume":{"brand":"Mont Blanc","name":"Patchouli Ink","sex":"unisex","image_url":"https://cdn2.randewoo.ru/img/488139/n/1","properties":{"perfume_type":"eau de parfum","family":["woody"],"upper_notes":["bergamot"],"core_notes":["blueberry"],"base_notes":["patchouli","vanilla"],"upper_tags":["cold","cool","salty","fresh","bright","light","marine","sharp","bold","noble","invigorating","airy"],"core_tags":["soft","bright","powdery","salty","fresh","green","bitter","sensual","rich","cool","elegant","sweet","light","dry","romantic","energetic"],"base_tags":["mysterious","dense","warm","sensual","romantic","rich","energetic","invigorating"],"upper_characteristics":{"density":0.15,"earthiness":0.15,"floralcy":0.15,"freshness":0.85,"fruityness":0.15,"powderiness":0.15,"spiciness":0.15,"sweetness":0.15,"warmth":0.15,"woodiness":0.15},"core_characteristics":{"density":0.15,"earthiness":0.15,"floralcy":0.15,"freshness":0.15,"fruityness":0.85,"powderiness":0.15,"spiciness":0.15,"sweetness":0.15,"warmth":0.15,"woodiness":0.15},"base_characteristics":{"density":0.15,"earthiness":0.5,"floralcy":0.15,"freshness":0.15,"fruityness":0.15,"powderiness":0.15,"spiciness":0.15,"sweetness":0.5,"warmth":0.5,"woodiness":0.15}},"shops":[{"shop_name":"Randewoo","domain":"https://randewoo.ru","variants":[{"volume":125,"link":"https://randewoo.ru/product/patchouli-ink?source_category=6\u0026preferred=488139","price":14171}]}]},"rank":1,"similarity_score":0.8615160535935265},{"perfume":{"brand":"DILIS","name":"Seduisant","sex":"male","image_url":"https://pcdn.goldapple.ru/p/p/19000390678/imgmain_11db3652a5dc4a1fbd03aa5a2afd11b5.jpg","properties":{"perfume_type":"eau de parfum","family":["fresh","woody"],"upper_notes":["citrus","lavender","nootka"],"core_notes":["apple","geranium"],"base_notes":["bohea","patchouli","tonka beans"],"upper_tags":["bright","resinous","sharp","light","cool","fresh","airy","energetic","marine"],"core_tags":["romantic","sensual","airy","bright","soft","fresh","elegant","cool","light","dry"],"base_tags":["rich","dense","warm","romantic","sensual","energetic","mysterious"],"upper_characteristics":{"density":0.15,"earthiness":0.15,"floralcy":0.15,"freshness":0.3833333333333333,"fruityness":0.15,"powderiness":0.15,"spiciness":0.15,"sweetness":0.15,"warmth":0.15,"woodiness":0.15},"core_characteristics":{"density":0.15,"earthiness":0.15,"floralcy":0.15,"freshness":0.15,"fruityness":0.5,"powderiness":0.15,"spiciness":0.15,"sweetness":0.15,"warmth":0.15,"woodiness":0.15},"base_characteristics":{"density":0.15,"earthiness":0.3833333333333333,"floralcy":0.15,"freshness":0.15,"fruityness":0.15,"powderiness":0.15,"spiciness":0.15,"sweetness":0.15,"warmth":0.3833333333333333,"woodiness":0.15}},"shops":[{"shop_name":"Gold Apple","domain":"https://goldapple.ru","variants":[{"volume":100,"link":"https://goldapple.ru/19000390678-seduisant","price":2505}]}]},"rank":2,"similarity_score":0.848146812145386},{"perfume":{"brand":"BOULEVARD","name":"GRANDS BOULEVARDS","sex":"male","image_url":"https://pcdn.goldapple.ru/p/p/19000306778/imgmain_6489b60bfadf4944b0baeb9288c9f25e.jpg","properties":{"perfume_type":"eau de parfum","family":["fresh"],"upper_notes":["bergamot","lemon","orange"],"core_notes":["fruity"],"base_notes":["amber","musk","vanilla"],"upper_tags":["airy","bright","cool","invigorating","light","fresh","salty"],"core_tags":["powdery","fresh","romantic","invigorating","green","sweet","bright","sensual","soft","bitter","elegant","airy","cool","light","salty","energetic","dry"],"base_tags":["mysterious","cozy","dense","dry","energetic","warm","rich"],"upper_characteristics":{"density":0.15,"earthiness":0.15,"floralcy":0.15,"freshness":0.6166666666666666,"fruityness":0.15,"powderiness":0.15,"spiciness":0.15,"sweetness":0.15,"warmth":0.15,"woodiness":0.15},"core_characteristics":{"density":0.15,"earthiness":0.15,"floralcy":0.15,"freshness":0.15,"fruityness":0.85,"powderiness":0.15,"spiciness":0.15,"sweetness":0.15,"warmth":0.15,"woodiness":0.15},"base_characteristics":{"density":0.3833333333333333,"earthiness":0.15,"floralcy":0.15,"freshness":0.15,"fruityness":0.15,"powderiness":0.3833333333333333,"spiciness":0.15,"sweetness":0.3833333333333333,"warmth":0.6166666666666667,"woodiness":0.15}},"shops":[{"shop_name":"Gold Apple","domain":"https://goldapple.ru","variants":[{"volume":100,"link":"https://goldapple.ru/19000306778-grands-boulevards","price":3890}]}]},"rank":3,"similarity_score":0.8430913574714065},{"perfume":{"brand":"Signature","name":"Jade","sex":"unisex","image_url":"https://cdn2.randewoo.ru/img/230559/n/1","properties":{"perfume_type":"набор (п/вода","family":["amber"],"upper_notes":["bergamot","lemon","orange"],"core_notes":["fruity"],"base_notes":["amber","musk","vanilla"],"upper_tags":["fresh","salty","cool","airy","light","invigorating","bright"],"core_tags":["salty","soft","sensual","invigorating","fresh","light","energetic","green","powdery","elegant","bright","sweet","romantic","cool","dry","airy","bitter"],"base_tags":["cozy","dry","warm","energetic","mysterious","dense","rich"],"upper_characteristics":{"density":0.15,"earthiness":0.15,"floralcy":0.15,"freshness":0.6166666666666666,"fruityness":0.15,"powderiness":0.15,"spiciness":0.15,"sweetness":0.15,"warmth":0.15,"woodiness":0.15},"core_characteristics":{"density":0.15,"earthiness":0.15,"floralcy":0.15,"freshness":0.15,"fruityness":0.85,"powderiness":0.15,"spiciness":0.15,"sweetness":0.15,"warmth":0.15,"woodiness":0.15},"base_characteristics":{"density":0.3833333333333333,"earthiness":0.15,"floralcy":0.15,"freshness":0.15,"fruityness":0.15,"powderiness":0.3833333333333333,"spiciness":0.15,"sweetness":0.3833333333333333,"warmth":0.6166666666666667,"woodiness":0.15}},"shops":[]},"rank":4,"similarity_score":0.8430913574714064}]},{"input":{"brand":"100BON","name":"Ambre Sensuel","sex":"unisex","image_url":"https://pcdn.goldapple.ru/p/p/19000159052/imgmain.jpg","properties":{"perfume_type":"eau de toilette","family":["amber","woody"],"upper_notes":["rose"],"core_notes":["amber"],"base_notes":["patchouli"],"upper_tags":["elegant","sweet","dense","invigorating","clean","airy","fruity","dry","warm","caramel","romantic","sensual","energetic","cozy","mysterious","resinous","rich","soft","calm","light"],"core_tags":["rich","cozy","dry","energetic","earthy","warm","calm","dense","soapy","floral","mossy","mysterious"],"base_tags":["rich","floral","invigorating","energetic","clean","earthy","romantic","mysterious","mossy","sensual","woody","bold","leathery","warm","dense","fruity"],"upper_characteristics":{"density":0.15,"earthiness":0.15,"floralcy":0.85,"freshness":0.15,"fruityness":0.15,"powderiness":0.15,"spiciness":0.15,"sweetness":0.15,"warmth":0.15,"woodiness":0.15},"core_characteristics":{"density":0.85,"earthiness":0.15,"floralcy":0.15,"freshness":0.15,"fruityness":0.15,"powderiness":0.15,"spiciness":0.15,"sweetness":0.15,"warmth":0.85,"woodiness":0.15},"base_characteristics":{"density":0.15,"earthiness":0.85,"floralcy":0.15,"freshness":0.15,"fruityness":0.15,"powderiness":0.15,"spiciness":0.15,"sweetness":0.15,"warmth":0.15,"woodiness":0.15}},"shops":[{"shop_name":"Gold Apple","domain":"https://goldapple.ru","variants":[{"volume":50,"link":"https://goldapple.ru/19000159052-ambre-sensuel","price":5150}]}]},"suggestions":[{"perfume":{"brand":"Boadicea The Victorious","name":"Salubrious","sex":"unisex","image_url":"https://cdn2.randewoo.ru/img/30906/n/1","properties":{"perfume_type":"eau de parfum","family":["amber","floral"],"upper_notes":["geranium","orange","rose"],"core_notes":["amber"],"base_notes":["incienso","patchouli","vetiver"],"upper_tags":["sensual","elegant","soft","dry","light","romantic","airy"],"core_tags":["calm","soapy","cozy","dense","earthy","warm","energetic","mossy","rich","mysterious","dry","floral"],"base_tags":["floral","energetic","mysterious","warm","rich","mossy","dense","earthy"],"upper_characteristics":{"density":0.15,"earthiness":0.15,"floralcy":0.3833333333333333,"freshness":0.15,"fruityness":0.15,"powderiness":0.15,"spiciness":0.15,"sweetness":0.15,"warmth":0.15,"woodiness":0.15},"core_characteristics":{"density":0.85,"earthiness":0.15,"floralcy":0.15,"freshness":0.15,"fruityness":0.15,"powderiness":0.15,"spiciness":0.15,"sweetness":0.15,"warmth":0.85,"woodiness":0.15},"base_characteristics":{"density":0.15,"earthiness":0.6166666666666667,"floralcy":0.15,"freshness":0.15,"fruityness":0.15,"powderiness":0.15,"spiciness":0.15,"sweetness":0.15,"warmth":0.15,"woodiness":0.15}},"shops":[{"shop_name":"Randewoo","domain":"https://randewoo.ru","variants":[{"volume":100,"link":"https://randewoo.ru/product/boadicea-the-victorious-salubrious?source_category=6\u0026preferred=30906","price":0}]}]},"rank":1,"similarity_score":0.8730621670138135},{"perfume":{"brand":"Bohoboco","name":"Yellow Rose Incense","sex":"unisex","image_url":"https://cdn2.randewoo.ru/img/444196/n/1","properties":{"perfume_type":"parfum","family":["amber","floral","woody"],"upper_notes":["cinnamon","dianthus","rose"],"core_notes":["amber","incienso","oud"],"base_notes":["benzoin","patchouli"],"upper_tags":["dry"],"core_tags":["floral","dense","soapy","mysterious","earthy","dry","energetic","cozy","rich","mossy","warm","calm"],"base_tags":["rich","mysterious","dense","clean","romantic","mossy","energetic","invigorating","floral","earthy","sensual","warm"],"upper_characteristics":{"density":0.15,"earthiness":0.15,"floralcy":0.3833333333333333,"freshness":0.15,"fruityness":0.15,"powderiness":0.15,"spiciness":0.3833333333333333,"sweetness":0.15,"warmth":0.15,"woodiness":0.15},"core_characteristics":{"density":0.6166666666666667,"earthiness":0.15,"floralcy":0.15,"freshness":0.15,"fruityness":0.15,"powderiness":0.15,"spiciness":0.15,"sweetness":0.15,"warmth":0.3833333333333333,"woodiness":0.15},"base_characteristics":{"density":0.15,"earthiness":0.5,"floralcy":0.15,"freshness":0.15,"fruityness":0.15,"powderiness":0.15,"spiciness":0.15,"sweetness":0.15,"warmth":0.15,"woodiness":0.15}},"shops":[{"shop_name":"Randewoo","domain":"https://randewoo.ru","variants":[{"volume":50,"link":"https://randewoo.ru/product/yellow-rose-incense?source_category=6\u0026preferred=444196","price":12297}]}]},"rank":2,"similarity_score":0.8504401155736645},{"perfume":{"brand":"Zielinski \u0026 Rozen","name":"tobacco, amber, patchouli","sex":"unisex","image_url":"https://pcdn.goldapple.ru/p/p/19000084111/imgmain_8c223112f35f4bd397bbf171020d2cab.jpg","properties":{"perfume_type":"parfum","family":["amber"],"upper_notes":["tobacco"],"core_notes":["amber"],"base_notes":["patchouli"],"upper_tags":["mysterious","bold","dense","fruity","invigorating","sensual","clean","romantic","warm","earthy","floral","woody","energetic","rich","soapy","mossy"],"core_tags":["dense","mossy","dry","cozy","warm","energetic","earthy","mysterious","soapy","calm","rich","floral"],"base_tags":["mysterious","romantic","dense","clean","fruity","sensual","invigorating","rich","energetic","earthy","mossy","leathery","woody","bold","floral","warm"],"upper_characteristics":{"density":0.15,"earthiness":0.15,"floralcy":0.15,"freshness":0.15,"fruityness":0.15,"powderiness":0.15,"spiciness":0.15,"sweetness":0.15,"warmth":0.15,"woodiness":0.15},"core_characteristics":{"density":0.85,"earthiness":0.15,"floralcy":0.15,"freshness":0.15,"fruityness":0.15,"powderiness":0.15,"spiciness":0.15,"sweetness":0.15,"warmth":0.85,"woodiness":0.15},"base_characteristics":{"density":0.15,"earthiness":0.85,"floralcy":0.15,"freshness":0.15,"fruityness":0.15,"powderiness":0.15,"spiciness":0.15,"sweetness":0.15,"warmth":0.15,"woodiness":0.15}},"shops":[{"shop_name":"Gold Apple","domain":"https://goldapple.ru","variants":[{"volume":10,"link":"https://goldapple.ru/19000084110-tobacco-amber-patchouli","price":2690},{"volume":50,"link":"https://goldapple.ru/19000084111-tobacco-amber-patchouli","price":7350}]}]},"rank":3,"similarity_score":0.8503276072267354},{"perfume":{"brand":"Zielinski \u0026 Rozen","name":"Amber, Patchouli","sex":"unisex","image_url":"https://pcdn.goldapple.ru/p/p/19000021493/imgmain_cbb9c38ecaa84a45b88798dbc432f62f.jpg","properties":{"perfume_type":"parfum","family":["woody"],"upper_notes":["tobacco"],"core_notes":["amber"],"base_notes":["patchouli"],"upper_tags":["invigorating","energetic","warm","fruity","floral","soapy","clean","mossy","dense","bold","earthy","woody","mysterious","sensual","romantic","rich"],"core_tags":["soapy","energetic","mossy","mysterious","earthy","dense","warm","cozy","dry","calm","rich","floral"],"base_tags":["fruity","mysterious","earthy","leathery","sensual","woody","dense","warm","romantic","clean","energetic","invigorating","bold","mossy","floral","rich"],"upper_characteristics":{"density":0.15,"earthiness":0.15,"floralcy":0.15,"freshness":0.15,"fruityness":0.15,"powderiness":0.15,"spiciness":0.15,"sweetness":0.15,"warmth":0.15,"woodiness":0.15},"core_characteristics":{"density":0.85,"earthiness":0.15,"floralcy":0.15,"freshness":0.15,"fruityness":0.15,"powderiness":0.15,"spiciness":0.15,"sweetness":0.15,"warmth":0.85,"woodiness":0.15},"base_characteristics":{"density":0.15,"earthiness":0.85,"floralcy":0.15,"freshness":0.15,"fruityness":0.15,"powderiness":0.15,"spiciness":0.15,"sweetness":0.15,"warmth":0.15,"woodiness":0.15}},"shops":[{"shop_name":"Gold Apple","domain":"https://goldapple.ru","variants":[{"volume":50,"link":"https://goldapple.ru/90151200001-moss","price":7350},{"volume":10,"link":"https://goldapple.ru/19000021493-moss","price":2690}]}]},"rank":4,"similarity_score":0.8503276072267354}]},{"input":{"brand":"Versace","name":"Versus Uomo","sex":"male","image_url":"https://cdn2.randewoo.ru/img/20643/n/1","properties":{"perfume_type":"eau de toilette","family":["amber","woody"],"upper_notes":["bergamot","lavender","lemon","lime","peach","tangerine"],"core_notes":["bark","coriander","dianthus","jasmine"],"base_notes":["benzoin","cedar","indian spices","musk","sandalwood"],"upper_tags":["fresh","airy","sharp","bright","marine","cool","invigorating","salty","light"],"core_tags":["resinous"],"base_tags":["mysterious","resinous","earthy","floral","mossy","dense","energetic","rich","warm"],"upper_characteristics":{"density":0.15,"earthiness":0.15,"floralcy":0.15,"freshness":0.5,"fruityness":0.26666666666666666,"powderiness":0.15,"spiciness":0.15,"sweetness":0.15,"warmth":0.15,"woodiness":0.15},"core_characteristics":{"density":0.15,"earthiness":0.15,"floralcy":0.32499999999999996,"freshness":0.15,"fruityness":0.15,"powderiness":0.15,"spiciness":0.15,"sweetness":0.15,"warmth":0.15,"woodiness":0.15},"base_characteristics":{"density":0.15,"earthiness":0.15,"floralcy":0.15,"freshness":0.15,"fruityness":0.15,"powderiness":0.2899999999999999,"spiciness":0.2899999999999999,"sweetness":0.15,"warmth":0.2899999999999999,"woodiness":0.43}},"shops":[{"shop_name":"Randewoo","domain":"https://randewoo.ru","variants":[{"volume":100,"link":"https://randewoo.ru/product/versace-versus-uomo?source_category=6\u0026preferred=20643","price":35647}]}]},"suggestions":[{"perfume":{"brand":"Comporta Perfumes","name":"Mosquito Man Extrait De Parfum","sex":"male","image_url":"https://cdn2.randewoo.ru/img/458755/n/1","properties":{"perfume_type":"parfum","family":["floral","fresh"],"upper_notes":["bergamot","citrus","galbanum","tangerine"],"core_notes":["bark","lily of the valley","syringa"],"base_notes":["cedar","musk","sandalwood"],"upper_tags":["invigorating","fresh","marine","light","salty","sharp","cold","airy","cool","bright"],"core_tags":["sensual","energetic","clean","resinous","romantic","airy"],"base_tags":["floral","mysterious","dense","mossy","rich","warm","earthy","energetic"],"upper_characteristics":{"density":0.15,"earthiness":0.15,"floralcy":0.15,"freshness":0.49999999999999994,"fruityness":0.15,"powderiness":0.15,"spiciness":0.15,"sweetness":0.15,"warmth":0.15,"woodiness":0.15},"core_characteristics":{"density":0.15,"earthiness":0.15,"floralcy":0.3833333333333333,"freshness":0.15,"fruityness":0.15,"powderiness":0.15,"spiciness":0.15,"sweetness":0.15,"warmth":0.15,"woodiness":0.15},"base_characteristics":{"density":0.15,"earthiness":0.15,"floralcy":0.15,"freshness":0.15,"fruityness":0.15,"powderiness":0.3833333333333333,"spiciness":0.15,"sweetness":0.15,"warmth":0.15,"woodiness":0.6166666666666667}},"shops":[{"shop_name":"Randewoo","domain":"https://randewoo.ru","variants":[{"volume":100,"link":"https://randewoo.ru/product/mosquito-man-extrait-de-parfum?source_category=6\u0026preferred=458755","price":0}]}]},"rank":1,"similarity_score":0.8701205463493612},{"perfume":{"brand":"Azzaro","name":"Chrome","sex":"male","image_url":"https://cdn2.randewoo.ru/img/17776/n/1","properties":{"perfume_type":"eau de toilette","family":["fresh"],"upper_notes":["bergamot","lemon","neroli","pineapple","rosemary"],"core_notes":["coriander","cyclamen","jasmine","oakmoss"],"base_notes":["cardamom","cedar","musk","oakmoss","sandalwood"],"upper_tags":["bright","fresh","cool","light","airy","invigorating","marine"],"core_tags":["resinous"],"base_tags":["mysterious","dense","mossy","energetic","earthy","floral","clean","warm","rich","resinous"],"upper_characteristics":{"density":0.15,"earthiness":0.15,"floralcy":0.29,"freshness":0.43,"fruityness":0.2899999999999999,"powderiness":0.15,"spiciness":0.15,"sweetness":0.15,"warmth":0.15,"woodiness":0.2899999999999999},"core_characteristics":{"density":0.15,"earthiness":0.32499999999999996,"floralcy":0.32499999999999996,"freshness":0.15,"fruityness":0.15,"powderiness":0.15,"spiciness":0.15,"sweetness":0.15,"warmth":0.15,"woodiness":0.32499999999999996},"base_characteristics":{"density":0.15,"earthiness":0.2899999999999999,"floralcy":0.15,"freshness":0.15,"fruityness":0.15,"powderiness":0.2899999999999999,"spiciness":0.2899999999999999,"sweetness":0.15,"warmth":0.15,"woodiness":0.5700000000000001}},"shops":[{"shop_name":"Randewoo","domain":"https://randewoo.ru","variants":[{"volume":100,"link":"https://randewoo.ru/product/azzaro-chrome?source_category=6\u0026preferred=17776","price":4689},{"volume":8,"link":"https://randewoo.ru/product/azzaro-chrome?source_category=6\u0026preferred=17776","price":787},{"volume":30,"link":"https://randewoo.ru/product/azzaro-chrome?source_category=6\u0026preferred=17776","price":3884},{"volume":200,"link":"https://randewoo.ru/product/azzaro-chrome?source_category=6\u0026preferred=17776","price":6814}]}]},"rank":2,"similarity_score":0.8697555114288129},{"perfume":{"brand":"Chris Collins","name":"Autumn Rhythm","sex":"unisex","image_url":"https://cdn2.randewoo.ru/img/394503/n/1","properties":{"perfume_type":"parfum","family":["woody"],"upper_notes":["bergamot"],"core_notes":["bark","lily of the valley","tea"],"base_notes":["ambrette","cedar","musk","skin"],"upper_tags":["fresh","light","airy","salty","noble","sharp","invigorating","bright","cold","marine","cool","bold"],"core_tags":["resinous","airy","energetic"],"base_tags":["floral","earthy","rich","mysterious","energetic","dry","velvety","mossy","soft","dense","warm"],"upper_characteristics":{"density":0.15,"earthiness":0.15,"floralcy":0.15,"freshness":0.85,"fruityness":0.15,"powderiness":0.15,"spiciness":0.15,"sweetness":0.15,"warmth":0.15,"woodiness":0.15},"core_characteristics":{"density":0.15,"earthiness":0.15,"floralcy":0.3833333333333333,"freshness":0.15,"fruityness":0.15,"powderiness":0.15,"spiciness":0.15,"sweetness":0.15,"warmth":0.15,"woodiness":0.15},"base_characteristics":{"density":0.15,"earthiness":0.15,"floralcy":0.15,"freshness":0.15,"fruityness":0.15,"powderiness":0.32499999999999996,"spiciness":0.15,"sweetness":0.15,"warmth":0.15,"woodiness":0.32499999999999996}},"shops":[{"shop_name":"Randewoo","domain":"https://randewoo.ru","variants":[{"volume":50,"link":"https://randewoo.ru/product/autumn-rhythm?source_category=6\u0026preferred=394503","price":0}]}]},"rank":3,"similarity_score":0.8665036621190632},{"perfume":{"brand":"Ferrari","name":"Scuderia Ferrari Red","sex":"male","image_url":"https://cdn2.randewoo.ru/img/181367/n/1","properties":{"perfume_type":"eau de toilette","family":["fresh"],"upper_notes":["bergamot","galbanum","mint","orange","petitgrain"],"core_notes":["bark","geranium","jasmine","nutmeg"],"base_notes":["cedar","moss","sandalwood","vanilla"],"upper_tags":["sharp","cool","bright","invigorating","light","cold","fresh","airy","marine"],"core_tags":["resinous","airy"],"base_tags":["dense","mossy","energetic","rich","warm","mysterious"],"upper_characteristics":{"density":0.15,"earthiness":0.15,"floralcy":0.15,"freshness":0.43,"fruityness":0.15,"powderiness":0.15,"spiciness":0.15,"sweetness":0.15,"warmth":0.15,"woodiness":0.15},"core_characteristics":{"density":0.15,"earthiness":0.15,"floralcy":0.32499999999999996,"freshness":0.15,"fruityness":0.15,"powderiness":0.15,"spiciness":0.15,"sweetness":0.15,"warmth":0.15,"woodiness":0.15},"base_characteristics":{"density":0.15,"earthiness":0.32499999999999996,"floralcy":0.15,"freshness":0.15,"fruityness":0.15,"powderiness":0.15,"spiciness":0.15,"sweetness":0.32499999999999996,"warmth":0.32499999999999996,"woodiness":0.5}},"shops":[{"shop_name":"Randewoo","domain":"https://randewoo.ru","variants":[{"volume":125,"link":"https://randewoo.ru/product/ferrari-scuderia-ferrari-red?source_category=6\u0026preferred=181367","price":4443}]}]},"rank":4,"similarity_score":0.8658704786346434}]},{"input":{"brand":"Aramis","name":"900","sex":"male","image_url":"https://cdn2.randewoo.ru/img/142239/n/1","properties":{"perfume_type":"eau de cologne","family":[],"upper_notes":["bergamot","coriander","lemon"],"core_notes":["dianthus","geranium","iris","jasmine","lily of the valley","rose"],"base_notes":["amber","civet","oakmoss","patchouli","sandalwood","vetiver"],"upper_tags":["salty","cool","invigorating","airy","cold","noble","fresh","bold","bright","sharp","marine","light"],"core_tags":["sensual","romantic","fruity","elegant","light","dry","soft","resinous","clean"],"base_tags":["energetic","dense","romantic","floral","warm","mossy","sensual","earthy","rich","mysterious","clean"],"upper_characteristics":{"density":0.15,"earthiness":0.15,"floralcy":0.15,"freshness":0.6166666666666667,"fruityness":0.15,"powderiness":0.15,"spiciness":0.15,"sweetness":0.15,"warmth":0.15,"woodiness":0.15},"core_characteristics":{"density":0.15,"earthiness":0.15,"floralcy":0.5,"freshness":0.15,"fruityness":0.15,"powderiness":0.2666666666666666,"spiciness":0.15,"sweetness":0.15,"warmth":0.15,"woodiness":0.15},"base_characteristics":{"density":0.2666666666666666,"earthiness":0.5,"floralcy":0.15,"freshness":0.15,"fruityness":0.15,"powderiness":0.15,"spiciness":0.15,"sweetness":0.15,"warmth":0.2666666666666666,"woodiness":0.3833333333333333}},"shops":[{"shop_name":"Randewoo","domain":"https://randewoo.ru","variants":[{"volume":100,"link":"https://randewoo.ru/product/aramis-900?source_category=6\u0026preferred=142239","price":31969}]}]},"suggestions":[{"perfume":{"brand":"Aramis","name":"900 Винтаж","sex":"male","image_url":"https://cdn2.randewoo.ru/img/35275/n/1","properties":{"perfume_type":"eau de cologne","family":["woody"],"upper_notes":["bergamot","coriander","lemon"],"core_notes":["bark","dianthus","geranium","jasmine","lily of the valley","rose"],"base_notes":["amber","civet","oakmoss","patchouli","sandalwood","vetiver"],"upper_tags":["light","bold","bright","salty","airy","marine","cold","noble","sharp","cool","fresh","invigorating"],"core_tags":["romantic","resinous","clean","sensual"],"base_tags":["energetic","dense","sensual","floral","warm","earthy","romantic","mysterious","rich","mossy","clean"],"upper_characteristics":{"density":0.15,"earthiness":0.15,"floralcy":0.15,"freshness":0.6166666666666667,"fruityness":0.15,"powderiness":0.15,"spiciness":0.15,"sweetness":0.15,"warmth":0.15,"woodiness":0.15},"core_characteristics":{"density":0.15,"earthiness":0.15,"floralcy":0.5,"freshness":0.15,"fruityness":0.15,"powderiness":0.15,"spiciness":0.15,"sweetness":0.15,"warmth":0.15,"woodiness":0.15},"base_characteristics":{"density":0.2666666666666666,"earthiness":0.5,"floralcy":0.15,"freshness":0.15,"fruityness":0.15,"powderiness":0.15,"spiciness":0.15,"sweetness":0.15,"warmth":0.2666666666666666,"woodiness":0.3833333333333333}},"shops":[{"shop_name":"Randewoo","domain":"https://randewoo.ru","variants":[{"volume":100,"link":"https://randewoo.ru/product/aramis-900-vintazh?source_category=6\u0026preferred=35275","price":31969}]}]},"rank":1,"similarity_score":0.8935927728081681},{"perfume":{"brand":"Gucci","name":"Nobile","sex":"male","image_url":"https://cdn2.randewoo.ru/img/24298/n/1","properties":{"perfume_type":"eau de toilette","family":["fresh"],"upper_notes":["bergamot","lavender","lemon","nutmeg","rosemary","tarragon"],"core_notes":["cyclamen","dianthus","geranium","jasmine","rose"],"base_notes":["amber","musk","oakmoss","patchouli","sandalwood","vetiver"],"upper_tags":["fresh","resinous","energetic","airy","marine","sharp","cool","bright","elegant","light"],"core_tags":["dry","light","soft","romantic","resinous","elegant","clean","sensual","fruity"],"base_tags":["dense","rich","sensual","leathery","romantic","mossy","earthy","mysterious","warm","floral","energetic","clean"],"upper_characteristics":{"density":0.15,"earthiness":0.15,"floralcy":0.26666666666666666,"freshness":0.3833333333333333,"fruityness":0.15,"powderiness":0.15,"spiciness":0.15,"sweetness":0.15,"warmth":0.15,"woodiness":0.15},"core_characteristics":{"density":0.15,"earthiness":0.15,"floralcy":0.43,"freshness":0.15,"fruityness":0.15,"powderiness":0.15,"spiciness":0.15,"sweetness":0.15,"warmth":0.15,"woodiness":0.15},"base_characteristics":{"density":0.2666666666666666,"earthiness":0.5,"floralcy":0.15,"freshness":0.15,"fruityness":0.15,"powderiness":0.2666666666666666,"spiciness":0.15,"sweetness":0.15,"warmth":0.2666666666666666,"woodiness":0.3833333333333333}},"shops":[{"shop_name":"Randewoo","domain":"https://randewoo.ru","variants":[{"volume":120,"link":"https://randewoo.ru/product/gucci-nobile?source_category=6\u0026preferred=24298","price":83875},{"volume":30,"link":"https://randewoo.ru/product/gucci-nobile?source_category=6\u0026preferred=24298","price":16462}]}]},"rank":2,"similarity_score":0.8851374026464476},{"perfume":{"brand":"Shiseido","name":"Enchanting Dance","sex":"unisex","image_url":"https://cdn2.randewoo.ru/img/33190/n/1","properties":{"perfume_type":"parfum","family":["floral","woody"],"upper_notes":["bergamot","cardamom","lemon"],"core_notes":["dianthus","honey","iris","jasmine","lily of the valley","tuberose","ylang-ylang"],"base_notes":["benzoin","civet","incienso","oakmoss","patchouli","sandalwood","vetiver"],"upper_tags":["cool","marine","salty","cold","bold","sharp","fresh","light","airy","invigorating","noble","bright"],"core_tags":["romantic","dry","sensual","soft"],"base_tags":["floral","mysterious","romantic","energetic","warm","dense","mossy","earthy","sensual","rich","clean"],"upper_characteristics":{"density":0.15,"earthiness":0.15,"floralcy":0.15,"freshness":0.6166666666666667,"fruityness":0.15,"powderiness":0.15,"spiciness":0.3833333333333333,"sweetness":0.15,"warmth":0.15,"woodiness":0.15},"core_characteristics":{"density":0.15,"earthiness":0.15,"floralcy":0.55,"freshness":0.15,"fruityness":0.15,"powderiness":0.24999999999999994,"spiciness":0.15,"sweetness":0.24999999999999994,"warmth":0.15,"woodiness":0.15},"base_characteristics":{"density":0.15,"earthiness":0.45,"floralcy":0.15,"freshness":0.15,"fruityness":0.15,"powderiness":0.15,"spiciness":0.15,"sweetness":0.15,"warmth":0.15,"woodiness":0.35}},"shops":[{"shop_name":"Randewoo","domain":"https://randewoo.ru","variants":[{"volume":20,"link":"https://randewoo.ru/product/shiseido-enchanting-dance?source_category=6\u0026preferred=33190","price":48927}]}]},"rank":3,"similarity_score":0.8841020494352638},{"perfume":{"brand":"Loewe","name":"Pour Homme","sex":"male","image_url":"https://cdn2.randewoo.ru/img/55738/n/1","properties":{"perfume_type":"eau de toilette","family":["fresh"],"upper_notes":["basil","lavender","lemon"],"core_notes":["geranium","lily of the valley"],"base_notes":["amber","oakmoss","sandalwood","vetiver"],"upper_tags":["marine","resinous","cold","cool","bright","sharp","elegant","airy","energetic","fresh","light"],"core_tags":["elegant","fresh","sensual","airy","resinous","soft","light","bright","romantic","dry","calm","clean","velvety","cool","marine","fruity"],"base_tags":["mossy","mysterious","rich","warm","energetic","dense","earthy","floral"],"upper_characteristics":{"density":0.15,"earthiness":0.15,"floralcy":0.15,"freshness":0.3833333333333333,"fruityness":0.15,"powderiness":0.15,"spiciness":0.15,"sweetness":0.15,"warmth":0.15,"woodiness":0.15},"core_characteristics":{"density":0.15,"earthiness":0.15,"floralcy":0.5,"freshness":0.15,"fruityness":0.15,"powderiness":0.15,"spiciness":0.15,"sweetness":0.15,"warmth":0.15,"woodiness":0.15},"base_characteristics":{"density":0.32499999999999996,"earthiness":0.5,"floralcy":0.15,"freshness":0.15,"fruityness":0.15,"powderiness":0.15,"spiciness":0.15,"sweetness":0.15,"warmth":0.32499999999999996,"woodiness":0.5}},"shops":[{"shop_name":"Randewoo","domain":"https://randewoo.ru","variants":[{"volume":150,"link":"https://randewoo.ru/product/loewe-pour-homme?source_category=6\u0026preferred=55738","price":14981},{"volume":100,"link":"https://randewoo.ru/product/loewe-pour-homme?source_category=6\u0026preferred=55738","price":11108}]}]},"rank":4,"similarity_score":0.8824401143817939}]}]}