{"weights":{"upper_notes_weight":0.15,"core_notes_weight":0.45,"base_notes_weight":0.4,"characteristics_weight":0.3,"tags_weight":0.4,"overlay_weight":0.3},"runs":[{"input":{"brand":"DIOR","name":"J'adore","sex":"female","image_url":"https://www.letu.ru/common/img/pim/2025/03/EX_eb6096da-5546-4018-887a-422656773396.jpg","properties":{"perfume_type":"eau de parfum","family":["floral"],"upper_notes":["bergamot","ylang-ylang"],"core_notes":["orchid","plum","rose"],"base_notes":["amaranth","jasmine","tobacco"],"upper_tags":["airy","invigorating","fresh","marine","light","bright","cool"],"base_tags":["clean","fruity","sensual","romantic"],"upper_characteristics":{"density":0.15,"earthiness":0.15,"floralcy":0.5,"freshness":0.5,"fruityness":0.15,"powderiness":0.15,"spiciness":0.15,"sweetness":0.15,"warmth":0.15,"woodiness":0.15},"core_characteristics":{"density":0.15,"earthiness":0.15,"floralcy":0.3833333333333333,"freshness":0.15,"fruityness":0.3833333333333333,"powderiness":0.15,"spiciness":0.15,"sweetness":0.15,"warmth":0.15,"woodiness":0.15},"base_characteristics":{"density":0.15,"earthiness":0.15,"floralcy":0.3833333333333333,"freshness":0.15,"fruityness":0.15,"powderiness":0.15,"spiciness":0.15,"sweetness":0.15,"warmth":0.15,"woodiness":0.15}},"shops":[{"shop_name":"Letu","domain":"https://www.letu.ru","variants":[{"volume":30,"link":"https://www.letu.ru/product/dior-j-adore/1114","price":9300}]},{"shop_name":"Gold Apple","domain":"https://goldapple.ru","variants":[{"volume":15,"link":"https://goldapple.ru/7190300064-j-adore","price":28600},{"volume":100,"link":"https://goldapple.ru/7190300009-j-adore","price":18750}]}]},"suggestions":[{"perfume":{"brand":"DIOR","name":"J'аdore Eau de Parfum Roller Pearl","sex":"female","image_url":"https://pcdn.goldapple.ru/p/p/7190300083/imgmain_b741230ae64e4e90ae973c514ef1183f.jpg","properties":{"perfume_type":"eau de parfum","family":["floral"],"upper_notes":["ylang-ylang"],"core_notes":["rose"],"base_notes":["jasmine","tobacco"],"core_tags":["elegant","sensual","soft","mysterious","airy","dry","rich","fruity","cozy","dense","clean","sweet","invigorating","light","romantic","calm","caramel","warm","energetic","resinous"],"base_tags":["sensual","romantic","energetic","invigorating","fruity","clean","mysterious"],"upper_characteristics":{"density":0.15,"earthiness":0.15,"floralcy":0.85,"freshness":0.15,"fruityness":0.15,"powderiness":0.15,"spiciness":0.15,"sweetness":0.15,"warmth":0.15,"woodiness":0.15},"core_characteristics":{"density":0.15,"earthiness":0.15,"floralcy":0.85,"freshness":0.15,"fruityness":0.15,"powderiness":0.15,"spiciness":0.15,"sweetness":0.15,"warmth":0.15,"woodiness":0.15},"base_characteristics":{"density":0.15,"earthiness":0.15,"floralcy":0.5,"freshness":0.15,"fruityness":0.15,"powderiness":0.15,"spiciness":0.15,"sweetness":0.15,"warmth":0.15,"woodiness":0.15}},"shops":[{"shop_name":"Gold Apple","domain":"https://goldapple.ru","variants":[{"volume":20,"link":"https://goldapple.ru/7190300083-j-adore","price":6650}]}]},"rank":1,"similarity_score":0.6541980207538538},{"perfume":{"brand":"Masaki Matsushima","name":"Mat; Limited","sex":"female","image_url":"https://cdn2.randewoo.ru/img/42178/n/1","properties":{"perfume_type":"eau de parfum","family":["floral","fresh"],"upper_notes":["bamboo","mango","pomegranate","tea"],"core_notes":["lotus","osmanthus","rose"],"base_notes":["jasmine","musk","starflower","vodka"],"upper_tags":["bright","light","fresh","energetic","cool","soft","airy"],"base_tags":["dry"],"upper_characteristics":{"density":0.15,"earthiness":0.15,"floralcy":0.15,"freshness":0.15,"fruityness":0.15,"powderiness":0.15,"spiciness":0.15,"sweetness":0.15,"warmth":0.15,"woodiness":0.15},"core_characteristics":{"density":0.15,"earthiness":0.15,"floralcy":0.3833333333333333,"freshness":0.15,"fruityness":0.15,"powderiness":0.15,"spiciness":0.15,"sweetness":0.15,"warmth":0.15,"woodiness":0.15},"base_characteristics":{"density":0.15,"earthiness":0.15,"floralcy":0.5,"freshness":0.15,"fruityness":0.15,"powderiness":0.32499999999999996,"spiciness":0.15,"sweetness":0.15,"warmth":0.15,"woodiness":0.15}},"shops":[{"shop_name":"Gold Apple","domain":"https://goldapple.ru","variants":[{"volume":10,"link":"https://goldapple.ru/19000088219-mat-limited","price":1850}]},{"shop_name":"Randewoo","domain":"https://randewoo.ru","variants":[{"volume":10,"link":"https://randewoo.ru/product/masaki-matsushima-mat-limited?source_category=6\u0026preferred=42178","price":1018},{"volume":40,"link":"https://randewoo.ru/product/masaki-matsushima-mat-limited?source_category=6\u0026preferred=42178","price":3060}]}]},"rank":2,"similarity_score":0.6528826671864794},{"perfume":{"brand":"Burberry","name":"My Burberry Blush","sex":"female","image_url":"https://cdn2.randewoo.ru/img/134613/n/1","properties":{"perfume_type":"eau de parfum","family":["floral"],"upper_notes":["lemon","pomegranate"],"core_notes":["apple","geranium","rose","soybean"],"base_notes":["jasmine","wisteria"],"upper_tags":["light","cool","airy","salty","fresh","invigorating","bright"],"core_tags":["dry","soft","light"],"base_tags":["calm","sensual","light","resinous","cool","bright","elegant","velvety","soft","fresh","dry","fruity","marine","airy","romantic","clean"],"upper_characteristics":{"density":0.15,"earthiness":0.15,"floralcy":0.15,"freshness":0.5,"fruityness":0.15,"powderiness":0.15,"spiciness":0.15,"sweetness":0.15,"warmth":0.15,"woodiness":0.15},"core_characteristics":{"density":0.15,"earthiness":0.15,"floralcy":0.32499999999999996,"freshness":0.15,"fruityness":0.32499999999999996,"powderiness":0.15,"spiciness":0.15,"sweetness":0.15,"warmth":0.15,"woodiness":0.15},"base_characteristics":{"density":0.15,"earthiness":0.15,"floralcy":0.5,"freshness":0.15,"fruityness":0.15,"powderiness":0.15,"spiciness":0.15,"sweetness":0.15,"warmth":0.15,"woodiness":0.15}},"shops":[{"shop_name":"Gold Apple","domain":"https://goldapple.ru","variants":[{"volume":50,"link":"https://goldapple.ru/19000312578-my-burberry-blush","price":12700}]},{"shop_name":"Randewoo","domain":"https://randewoo.ru","variants":[{"volume":50,"link":"https://randewoo.ru/product/burberry-my-burberry-blush?source_category=6\u0026preferred=134613","price":6249},{"volume":90,"link":"https://randewoo.ru/product/burberry-my-burberry-blush?source_category=6\u0026preferred=134613","price":8525},{"volume":8,"link":"https://randewoo.ru/product/burberry-my-burberry-blush?source_category=6\u0026preferred=134613","price":840},{"volume":30,"link":"https://randewoo.ru/product/burberry-my-burberry-blush?source_category=6\u0026preferred=134613","price":5056}]}]},"rank":3,"similarity_score":0.6499414377798034},{"perfume":{"brand":"Xerjoff","name":"More Than Words","sex":"unisex","image_url":"https://cdn2.randewoo.ru/img/19233/n/1","properties":{"perfume_type":"eau de parfum","family":["floral","woody"],"upper_notes":["bergamot"],"core_notes":["heliotrope","rose"],"base_notes":["cyclamen","jasmine"],"upper_tags":["fresh","cool","cold","sharp","bright","salty","airy","bold","invigorating","noble","light","marine"],"base_tags":["clean","resinous","romantic","fresh","bright","sensual","velvety","marine","cool","airy","elegant","fruity","dry","calm","soft","light"],"upper_characteristics":{"density":0.15,"earthiness":0.15,"floralcy":0.15,"freshness":0.85,"fruityness":0.15,"powderiness":0.15,"spiciness":0.15,"sweetness":0.15,"warmth":0.15,"woodiness":0.15},"core_characteristics":{"density":0.15,"earthiness":0.15,"floralcy":0.5,"freshness":0.15,"fruityness":0.15,"powderiness":0.5,"spiciness":0.15,"sweetness":0.15,"warmth":0.15,"woodiness":0.15},"base_characteristics":{"density":0.15,"earthiness":0.15,"floralcy":0.5,"freshness":0.15,"fruityness":0.15,"powderiness":0.15,"spiciness":0.15,"sweetness":0.15,"warmth":0.15,"woodiness":0.15}},"shops":[{"shop_name":"Randewoo","domain":"https://randewoo.ru","variants":[{"volume":100,"link":"https://randewoo.ru/product/xerjoff-join-the-club-more-than-words?source_category=6\u0026preferred=19233","price":16507},{"volume":50,"link":"https://randewoo.ru/product/xerjoff-join-the-club-more-than-words?source_category=6\u0026preferred=19233","price":9448}]}]},"rank":4,"similarity_score":0.6423075201374576}]},{"input":{"brand":"Dolce \u0026 Gabbana","name":"Devotion Eau De Parfum Intense","sex":"female","image_url":"https://cdn2.randewoo.ru/img/496652/n/1","properties":{"perfume_type":"eau de parfum","family":[],"upper_notes":["green forest"],"core_notes":["orange"],"base_notes":["vanilla"],"upper_tags":["light","dense","rich","wet","resinous","romantic","sensual","airy","warm","energetic","mossy","floral"],"core_tags":["green","dry","sweet","cool","fresh","soft","bright","romantic","energetic","airy","bitter","elegant","light","sensual","invigorating","salty","powdery"],"base_tags":["gourmand","energetic","dense","green","powdery","dry","romantic","bitter","calm","light","warm","soft","invigorating","velvety","mysterious","sensual","caramel","rich","sweet","cozy"],"upper_characteristics":{"density":0.15,"earthiness":0.15,"floralcy":0.15,"freshness":0.15,"fruityness":0.15,"powderiness":0.15,"spiciness":0.15,"sweetness":0.15,"warmth":0.15,"woodiness":0.15},"core_characteristics":{"density":0.15,"earthiness":0.15,"floralcy":0.15,"freshness":0.15,"fruityness":0.15,"powderiness":0.15,"spiciness":0.15,"sweetness":0.15,"warmth":0.15,"woodiness":0.15},"base_characteristics":{"density":0.15,"earthiness":0.15,"floralcy":0.15,"freshness":0.15,"fruityness":0.15,"powderiness":0.15,"spiciness":0.15,"sweetness":0.85,"warmth":0.85,"woodiness":0.15}},"shops":[{"shop_name":"Randewoo","domain":"https://randewoo.ru","variants":[{"volume":50,"link":"https://randewoo.ru/product/devotion-eau-de-parfum-intense?source_category=6\u0026preferred=496652","price":6564},{"volume":100,"link":"https://randewoo.ru/product/devotion-eau-de-parfum-intense?source_category=6\u0026preferred=496652","price":8510},{"volume":8,"link":"https://randewoo.ru/product/devotion-eau-de-parfum-intense?source_category=6\u0026preferred=496652","price":945},{"volume":30,"link":"https://randewoo.ru/product/devotion-eau-de-parfum-intense?source_category=6\u0026preferred=496652","price":6130}]}]},"suggestions":[{"perfume":{"brand":"BEAUTIFIC","name":"LONDON REBEL","sex":"female","image_url":"https://pcdn.goldapple.ru/p/p/19000067387/imgmain.jpg","properties":{"perfume_type":"parfum","family":["amber"],"upper_notes":["bohea","cocoa","coffee","tonka beans"],"core_notes":["orange"],"base_notes":["vanilla"],"upper_tags":["dry","dense","sensual","velvety","energetic","cozy","rich","romantic","warm"],"core_tags":["energetic","sweet","bitter","salty","fresh","green","invigorating","powdery","elegant","light","airy","bright","soft","romantic","sensual","dry","cool"],"base_tags":["powdery","dense","green","romantic","cozy","caramel","sweet","rich","velvety","warm","soft","dry","sensual","bitter","invigorating","light","gourmand","calm","energetic","mysterious"],"upper_characteristics":{"density":0.15,"earthiness":0.15,"floralcy":0.15,"freshness":0.15,"fruityness":0.15,"powderiness":0.15,"spiciness":0.15,"sweetness":0.15,"warmth":0.32499999999999996,"woodiness":0.15},"core_characteristics":{"density":0.15,"earthiness":0.15,"floralcy":0.15,"freshness":0.15,"fruityness":0.15,"powderiness":0.15,"spiciness":0.15,"sweetness":0.15,"warmth":0.15,"woodiness":0.15},"base_characteristics":{"density":0.15,"earthiness":0.15,"floralcy":0.15,"freshness":0.15,"fruityness":0.15,"powderiness":0.15,"spiciness":0.15,"sweetness":0.85,"warmth":0.85,"woodiness":0.15}},"shops":[{"shop_name":"Gold Apple","domain":"https://goldapple.ru","variants":[{"volume":10,"link":"https://goldapple.ru/19000067387-london-rebel","price":1144}]}]},"rank":1,"similarity_score":0.6737119681349247},{"perfume":{"brand":"Montale","name":"Chocolate Greedy","sex":"unisex","image_url":"https://cdn2.randewoo.ru/img/45376/n/1","properties":{"perfume_type":"eau de parfum","family":["amber"],"upper_notes":["bohea","cocoa","coffee","tonka beans"],"core_notes":["orange"],"base_notes":["vanilla"],"upper_tags":["warm","sensual","rich","dense","velvety","romantic","cozy","dry","energetic"],"core_tags":["cool","invigorating","soft","elegant","dry","fresh","sensual","bright","sweet","romantic","salty","energetic","light","airy","powdery","bitter","green"],"base_tags":["dense","velvety","mysterious","green","calm","bitter","rich","energetic","dry","sweet","cozy","romantic","caramel","invigorating","sensual","warm","gourmand","powdery","soft","light"],"upper_characteristics":{"density":0.15,"earthiness":0.15,"floralcy":0.15,"freshness":0.15,"fruityness":0.15,"powderiness":0.15,"spiciness":0.15,"sweetness":0.15,"warmth":0.32499999999999996,"woodiness":0.15},"core_characteristics":{"density":0.15,"earthiness":0.15,"floralcy":0.15,"freshness":0.15,"fruityness":0.15,"powderiness":0.15,"spiciness":0.15,"sweetness":0.15,"warmth":0.15,"woodiness":0.15},"base_characteristics":{"density":0.15,"earthiness":0.15,"floralcy":0.15,"freshness":0.15,"fruityness":0.15,"powderiness":0.15,"spiciness":0.15,"sweetness":0.85,"warmth":0.85,"woodiness":0.15}},"shops":[{"shop_name":"Gold Apple","domain":"https://goldapple.ru","variants":[{"volume":50,"link":"https://goldapple.ru/26163500002-chocolate-greedy","price":12500}]},{"shop_name":"Randewoo","domain":"https://randewoo.ru","variants":[{"volume":50,"link":"https://randewoo.ru/product/montale-chocolate-greedy?source_category=6\u0026preferred=45376","price":5322},{"volume":8,"link":"https://randewoo.ru/product/montale-chocolate-greedy?source_category=6\u0026preferred=45376","price":745},{"volume":20,"link":"https://randewoo.ru/product/montale-chocolate-greedy?source_category=6\u0026preferred=45376","price":5326},{"volume":100,"link":"https://randewoo.ru/product/montale-chocolate-greedy?source_category=6\u0026preferred=45376","price":7217}]}]},"rank":2,"similarity_score":0.6737119681349247},{"perfume":{"brand":"Ghost","name":"Orb Of Night Elixir","sex":"female","image_url":"https://cdn2.randewoo.ru/img/532569/n/1","properties":{"perfume_type":"parfum","family":[],"upper_notes":["cherry"],"core_notes":["orange"],"base_notes":["vanilla"],"upper_tags":["green","energetic","light","bitter","bright","powdery","sensual","romantic","fresh","dry","cool","sweet","elegant","soft"],"core_tags":["fresh","bright","powdery","green","romantic","sweet","energetic","airy","light","bitter","sensual","invigorating","dry","soft","elegant","salty","cool"],"base_tags":["cozy","velvety","dry","invigorating","energetic","caramel","warm","gourmand","light","green","sweet","soft","dense","calm","sensual","powdery","mysterious","bitter","rich","romantic"],"upper_characteristics":{"density":0.15,"earthiness":0.15,"floralcy":0.15,"freshness":0.15,"fruityness":0.15,"powderiness":0.15,"spiciness":0.15,"sweetness":0.15,"warmth":0.15,"woodiness":0.15},"core_characteristics":{"density":0.15,"earthiness":0.15,"floralcy":0.15,"freshness":0.15,"fruityness":0.15,"powderiness":0.15,"spiciness":0.15,"sweetness":0.15,"warmth":0.15,"woodiness":0.15},"base_characteristics":{"density":0.15,"earthiness":0.15,"floralcy":0.15,"freshness":0.15,"fruityness":0.15,"powderiness":0.15,"spiciness":0.15,"sweetness":0.85,"warmth":0.85,"woodiness":0.15}},"shops":[{"shop_name":"Randewoo","domain":"https://randewoo.ru","variants":[{"volume":75,"link":"https://randewoo.ru/product/orb-of-night-elixir?source_category=6\u0026preferred=532569","price":0}]}]},"rank":3,"similarity_score":0.658516401995451},{"perfume":{"brand":"Miu Miu","name":"Les Eaux A La Mode - Serial Player","sex":"female","image_url":"https://cdn2.randewoo.ru/img/382384/n/1","properties":{"perfume_type":"eau de toilette","family":[],"upper_notes":["litchi"],"core_notes":["orange"],"base_notes":["vanilla"],"upper_tags":["cool","elegant","light","energetic","soft","romantic","sensual","invigorating","bright","bitter","sweet","dry","powdery","salty","fresh","green"],"core_tags":["invigorating","fresh","salty","dry","powdery","soft","bitter","bright","green","elegant","airy","sweet","light","romantic","energetic","sensual","cool"],"base_tags":["warm","energetic","dense","powdery","calm","gourmand","sensual","soft","rich","dry","invigorating","mysterious","green","romantic","light","cozy","bitter","caramel","velvety","sweet"],"upper_characteristics":{"density":0.15,"earthiness":0.15,"floralcy":0.15,"freshness":0.15,"fruityness":0.15,"powderiness":0.15,"spiciness":0.15,"sweetness":0.15,"warmth":0.15,"woodiness":0.15},"core_characteristics":{"density":0.15,"earthiness":0.15,"floralcy":0.15,"freshness":0.15,"fruityness":0.15,"powderiness":0.15,"spiciness":0.15,"sweetness":0.15,"warmth":0.15,"woodiness":0.15},"base_characteristics":{"density":0.15,"earthiness":0.15,"floralcy":0.15,"freshness":0.15,"fruityness":0.15,"powderiness":0.15,"spiciness":0.15,"sweetness":0.85,"warmth":0.85,"woodiness":0.15}},"shops":[{"shop_name":"Randewoo","domain":"https://randewoo.ru","variants":[{"volume":50,"link":"https://randewoo.ru/product/les-eaux-a-la-mode-serial-player?source_category=6\u0026preferred=382384","price":5859}]}]},"rank":4,"similarity_score":0.6573205080756888}]},{"input":{"brand":"Dolce \u0026 Gabbana","name":"Dolce Lily","sex":"female","image_url":"https://cdn2.randewoo.ru/img/402925/n/1","properties":{"perfume_type":"eau de toilette","family":[],"upper_notes":["bergamot","passionfruit"],"core_notes":["lily","rose"],"base_notes":["musk","sandalwood","vanilla"],"upper_tags":["cool","fresh","bright","airy","invigorating","light","salty"],"base_tags":["mysterious","energetic","dense","cozy","romantic","warm","soft","sensual","rich"],"upper_characteristics":{"density":0.15,"earthiness":0.15,"floralcy":0.15,"freshness":0.5,"fruityness":0.5,"powderiness":0.15,"spiciness":0.15,"sweetness":0.15,"warmth":0.15,"woodiness":0.15},"core_characteristics":{"density":0.15,"earthiness":0.15,"floralcy":0.85,"freshness":0.15,"fruityness":0.15,"powderiness":0.15,"spiciness":0.15,"sweetness":0.15,"warmth":0.15,"woodiness":0.15},"base_characteristics":{"density":0.15,"earthiness":0.15,"floralcy":0.15,"freshness":0.15,"fruityness":0.15,"powderiness":0.3833333333333333,"spiciness":0.15,"sweetness":0.3833333333333333,"warmth":0.3833333333333333,"woodiness":0.3833333333333333}},"shops":[{"shop_name":"Randewoo","domain":"https://randewoo.ru","variants":[{"volume":8,"link":"https://randewoo.ru/product/dolce-lily?source_category=6\u0026preferred=402925","price":645},{"volume":50,"link":"https://randewoo.ru/product/dolce-lily?source_category=6\u0026preferred=402925","price":3241},{"volume":5,"link":"https://randewoo.ru/product/dolce-lily?source_category=6\u0026preferred=402925","price":1391},{"volume":75,"link":"https://randewoo.ru/product/dolce-lily?source_category=6\u0026preferred=402925","price":6068}]}]},"suggestions":[{"perfume":{"brand":"Dolce \u0026 Gabbana","name":"Dolce Lily Eau de Toilette","sex":"female","image_url":"https://pcdn.goldapple.ru/p/p/19000039297/imgmain.jpg","properties":{"perfume_type":"eau de toilette","family":["floral"],"upper_notes":["bergamot","passionfruit"],"core_notes":["lily","peony","rose"],"base_notes":["musk","sandalwood","vanilla"],"upper_tags":["invigorating","cool","light","fresh","salty","airy","bright"],"core_tags":["invigorating","airy","clean","light","dry","soft","calm","resinous","romantic","fruity","energetic","elegant","sensual"],"base_tags":["cozy","mysterious","sensual","energetic","romantic","warm","soft","rich","dense"],"upper_characteristics":{"density":0.15,"earthiness":0.15,"floralcy":0.15,"freshness":0.5,"fruityness":0.5,"powderiness":0.15,"spiciness":0.15,"sweetness":0.15,"warmth":0.15,"woodiness":0.15},"core_characteristics":{"density":0.15,"earthiness":0.15,"floralcy":0.6166666666666667,"freshness":0.15,"fruityness":0.15,"powderiness":0.15,"spiciness":0.15,"sweetness":0.15,"warmth":0.15,"woodiness":0.15},"base_characteristics":{"density":0.15,"earthiness":0.15,"floralcy":0.15,"freshness":0.15,"fruityness":0.15,"powderiness":0.3833333333333333,"spiciness":0.15,"sweetness":0.3833333333333333,"warmth":0.3833333333333333,"woodiness":0.3833333333333333}},"shops":[{"shop_name":"Gold Apple","domain":"https://goldapple.ru","variants":[{"volume":75,"link":"https://goldapple.ru/19000039297-dolce-lily-eau-de-toilette","price":14800}]}]},"rank":1,"similarity_score":0.6932073299032644},{"perfume":{"brand":"WIDIAN AJ Arabia","name":"IV","sex":"unisex","image_url":"https://cdn2.randewoo.ru/img/22949/n/1","properties":{"perfume_type":"parfum","family":["amber"],"upper_notes":["bergamot","black currant","plum"],"core_notes":["rose"],"base_notes":["musk","sandalwood","skin","vanilla"],"upper_tags":["light","invigorating","salty"],"core_tags":["calm","sensual","mysterious","warm","invigorating","romantic","elegant","cozy","airy","resinous","sweet","clean","rich","dense","fruity","soft","dry","light","energetic","caramel"],"base_tags":["soft","dense","rich","warm"],"upper_characteristics":{"density":0.15,"earthiness":0.15,"floralcy":0.15,"freshness":0.3833333333333333,"fruityness":0.3833333333333333,"powderiness":0.15,"spiciness":0.15,"sweetness":0.15,"warmth":0.15,"woodiness":0.15},"core_characteristics":{"density":0.15,"earthiness":0.15,"floralcy":0.85,"freshness":0.15,"fruityness":0.15,"powderiness":0.15,"spiciness":0.15,"sweetness":0.15,"warmth":0.15,"woodiness":0.15},"base_characteristics":{"density":0.15,"earthiness":0.15,"floralcy":0.15,"freshness":0.15,"fruityness":0.15,"powderiness":0.32499999999999996,"spiciness":0.15,"sweetness":0.32499999999999996,"warmth":0.32499999999999996,"woodiness":0.32499999999999996}},"shops":[{"shop_name":"Randewoo","domain":"https://randewoo.ru","variants":[{"volume":50,"link":"https://randewoo.ru/product/widian-aj-arabia-iv?source_category=6\u0026preferred=22949","price":20736}]}]},"rank":2,"similarity_score":0.6901614292187298},{"perfume":{"brand":"Jacomo","name":"Le Parfum","sex":"female","image_url":"https://cdn2.randewoo.ru/img/12480/n/1","properties":{"perfume_type":"eau de parfum","family":["amber","floral","fresh"],"upper_notes":["bergamot","peach","tangerine"],"core_notes":["jasmine","rose"],"base_notes":["musk","sandalwood","vanilla"],"upper_tags":["salty","fresh","invigorating","light","bright","airy","cool"],"core_tags":["soft","clean","light","sensual","airy","energetic","calm","invigorating","dry","elegant","resinous","romantic","fruity","mysterious"],"base_tags":["energetic","romantic","cozy","soft","sensual","warm","mysterious","rich","dense"],"upper_characteristics":{"density":0.15,"earthiness":0.15,"floralcy":0.15,"freshness":0.3833333333333333,"fruityness":0.3833333333333333,"powderiness":0.15,"spiciness":0.15,"sweetness":0.15,"warmth":0.15,"woodiness":0.15},"core_characteristics":{"density":0.15,"earthiness":0.15,"floralcy":0.85,"freshness":0.15,"fruityness":0.15,"powderiness":0.15,"spiciness":0.15,"sweetness":0.15,"warmth":0.15,"woodiness":0.15},"base_characteristics":{"density":0.15,"earthiness":0.15,"floralcy":0.15,"freshness":0.15,"fruityness":0.15,"powderiness":0.3833333333333333,"spiciness":0.15,"sweetness":0.3833333333333333,"warmth":0.3833333333333333,"woodiness":0.3833333333333333}},"shops":[{"shop_name":"Randewoo","domain":"https://randewoo.ru","variants":[{"volume":100,"link":"https://randewoo.ru/product/jacomo-le-parfum?source_category=6\u0026preferred=12480","price":6324}]}]},"rank":3,"similarity_score":0.686952557808815},{"perfume":{"brand":"Rania J","name":"Rose Ishtar","sex":"female","image_url":"https://cdn2.randewoo.ru/img/35118/n/1","properties":{"perfume_type":"eau de parfum","family":["amber","floral"],"upper_notes":["bergamot","black currant"],"core_notes":["rose"],"base_notes":["heliotrope","musk","patchouli","sandalwood","vanilla"],"upper_tags":["cool","fresh","bright","light","airy","invigorating","salty"],"core_tags":["airy","soft","sensual","rich","resinous","elegant","warm","sweet","romantic","energetic","dense","clean","caramel","light","cozy","dry","calm","fruity","invigorating","mysterious"],"base_tags":["warm","dense","sensual","romantic","rich","mysterious","energetic"],"upper_characteristics":{"density":0.15,"earthiness":0.15,"floralcy":0.15,"freshness":0.5,"fruityness":0.15,"powderiness":0.15,"spiciness":0.15,"sweetness":0.15,"warmth":0.15,"woodiness":0.15},"core_characteristics":{"density":0.15,"earthiness":0.15,"floralcy":0.85,"freshness":0.15,"fruityness":0.15,"powderiness":0.15,"spiciness":0.15,"sweetness":0.15,"warmth":0.15,"woodiness":0.15},"base_characteristics":{"density":0.15,"earthiness":0.2899999999999999,"floralcy":0.15,"freshness":0.15,"fruityness":0.15,"powderiness":0.43,"spiciness":0.15,"sweetness":0.29,"warmth":0.29,"woodiness":0.2899999999999999}},"shops":[{"shop_name":"Randewoo","domain":"https://randewoo.ru","variants":[{"volume":50,"link":"https://randewoo.ru/product/rania-j-rose-ishtar?source_category=6\u0026preferred=35118","price":7010}]}]},"rank":4,"similarity_score":0.6867677022961676}]},{"input":{"brand":"1907","name":"Cedar Blue","sex":"male","image_url":"https://cdn2.randewoo.ru/img/440180/n/1","properties":{"perfume_type":"eau de parfum","family":["fresh","woody"],"upper_notes":["bergamot","grapefruit","lemon","mint","tangerine","thyme"],"core_notes":["aquatic notes","melon"],"base_notes":["amber","cedar","oakmoss","patchouli","sandalwood"],"upper_tags":["noble","bright","cold","salty","airy","bold","invigorating","light","fresh","sharp","marine","cool"],"core_tags":["bright","fresh","cool","light","airy"],"base_tags":["energetic","rich","warm","floral","earthy","mysterious","mossy","dense"],"upper_characteristics":{"density":0.15,"earthiness":0.15,"floralcy":0.15,"freshness":0.5,"fruityness":0.2666666666666666,"powderiness":0.15,"spiciness":0.15,"sweetness":0.15,"warmth":0.15,"woodiness":0.15},"core_characteristics":{"density":0.15,"earthiness":0.15,"floralcy":0.15,"freshness":0.15,"fruityness":0.15,"powderiness":0.15,"spiciness":0.15,"sweetness":0.15,"warmth":0.15,"woodiness":0.15},"base_characteristics":{"density":0.2899999999999999,"earthiness":0.43,"floralcy":0.15,"freshness":0.15,"fruityness":0.15,"powderiness":0.15,"spiciness":0.15,"sweetness":0.15,"warmth":0.2899999999999999,"woodiness":0.5700000000000001}},"shops":[{"shop_name":"Randewoo","domain":"https://randewoo.ru","variants":[{"volume":100,"link":"https://randewoo.ru/product/cedar-blue?source_category=6\u0026preferred=440180","price":15920}]}]},"suggestions":[{"perfume":{"brand":"Yves Saint Laurent","name":"L'Homme Cologne Bleue","sex":"male","image_url":"https://cdn2.randewoo.ru/img/185430/n/1","properties":{"perfume_type":"eau de toilette","family":[],"upper_notes":["bergamot","cardamom","grapefruit","tangerine"],"core_notes":["apple","aquatic notes","geranium","lavender","thyme"],"base_notes":["cedar","patchouli","sandalwood"],"upper_tags":["bright","cool","marine","salty","sharp","fresh","light","invigorating","airy"],"core_tags":["fresh","cool","bright","light","elegant","airy"],"base_tags":["mossy","mysterious","floral","dense","energetic","warm","rich","earthy"],"upper_characteristics":{"density":0.15,"earthiness":0.15,"floralcy":0.15,"freshness":0.32499999999999996,"fruityness":0.32499999999999996,"powderiness":0.15,"spiciness":0.32499999999999996,"sweetness":0.15,"warmth":0.15,"woodiness":0.15},"core_characteristics":{"density":0.15,"earthiness":0.15,"floralcy":0.15,"freshness":0.15,"fruityness":0.2899999999999999,"powderiness":0.15,"spiciness":0.15,"sweetness":0.15,"warmth":0.15,"woodiness":0.15},"base_characteristics":{"density":0.15,"earthiness":0.3833333333333333,"floralcy":0.15,"freshness":0.15,"fruityness":0.15,"powderiness":0.15,"spiciness":0.15,"sweetness":0.15,"warmth":0.15,"woodiness":0.6166666666666667}},"shops":[{"shop_name":"Randewoo","domain":"https://randewoo.ru","variants":[{"volume":100,"link":"https://randewoo.ru/product/yves-saint-laurent-l-homme-cologne-bleue?source_category=6\u0026preferred=185430","price":12118}]}]},"rank":1,"similarity_score":0.666438151643269},{"perfume":{"brand":"Gucci","name":"Guilty Pour Homme Platinum","sex":"male","image_url":"https://cdn2.randewoo.ru/img/91340/n/1","properties":{"perfume_type":"eau de toilette","family":["fresh","woody"],"upper_notes":["lavender","lemon"],"core_notes":["orange"],"base_notes":["cedar","patchouli"],"upper_tags":["bright","marine","cool","light","fresh","sharp","airy"],"core_tags":["sweet","energetic","salty","green","bitter","fresh","sensual","soft","invigorating","romantic","cool","dry","elegant","airy","light","powdery","bright"],"base_tags":["floral","energetic","earthy","warm","rich","mossy","mysterious","dense"],"upper_characteristics":{"density":0.15,"earthiness":0.15,"floralcy":0.15,"freshness":0.5,"fruityness":0.15,"powderiness":0.15,"spiciness":0.15,"sweetness":0.15,"warmth":0.15,"woodiness":0.15},"core_characteristics":{"density":0.15,"earthiness":0.15,"floralcy":0.15,"freshness":0.15,"fruityness":0.15,"powderiness":0.15,"spiciness":0.15,"sweetness":0.15,"warmth":0.15,"woodiness":0.15},"base_characteristics":{"density":0.15,"earthiness":0.5,"floralcy":0.15,"freshness":0.15,"fruityness":0.15,"powderiness":0.15,"spiciness":0.15,"sweetness":0.15,"warmth":0.15,"woodiness":0.5}},"shops":[{"shop_name":"Randewoo","domain":"https://randewoo.ru","variants":[{"volume":90,"link":"https://randewoo.ru/product/gucci-guilty-pour-homme-platinum?source_category=6\u0026preferred=91340","price":25364}]}]},"rank":2,"similarity_score":0.6621589830620517},{"perfume":{"brand":"Jul et Mad Paris","name":"Aqua Sextius","sex":"unisex","image_url":"https://cdn2.randewoo.ru/img/10960/n/1","properties":{"perfume_type":"parfum","family":["fresh"],"upper_notes":["bergamot","grapefruit","lemon","orange"],"core_notes":["aquatic notes","eucalyptus","fig","mimosa","mint"],"base_notes":["amber","cedar","guaiac","incienso","musk","oakmoss"],"upper_tags":["bold","salty","noble","sharp","cold","marine","airy","fresh","cool","invigorating","bright","light"],"core_tags":["airy","invigorating","light"],"base_tags":["mossy","warm","earthy","mysterious","dense","rich","floral","energetic"],"upper_characteristics":{"density":0.15,"earthiness":0.15,"floralcy":0.15,"freshness":0.5,"fruityness":0.32499999999999996,"powderiness":0.15,"spiciness":0.15,"sweetness":0.15,"warmth":0.15,"woodiness":0.15},"core_characteristics":{"density":0.15,"earthiness":0.15,"floralcy":0.15,"freshness":0.29,"fruityness":0.15,"powderiness":0.15,"spiciness":0.15,"sweetness":0.15,"warmth":0.15,"woodiness":0.15},"base_characteristics":{"density":0.2666666666666666,"earthiness":0.26666666666666666,"floralcy":0.15,"freshness":0.15,"fruityness":0.15,"powderiness":0.26666666666666666,"spiciness":0.15,"sweetness":0.15,"warmth":0.2666666666666666,"woodiness":0.5}},"shops":[{"shop_name":"Randewoo","domain":"https://randewoo.ru","variants":[{"volume":50,"link":"https://randewoo.ru/product/jul-et-mad-paris-aqua-sextius?source_category=6\u0026preferred=10960","price":22240}]}]},"rank":3,"similarity_score":0.6585496595885424},{"perfume":{"brand":"Carner Barcelona","name":"Helix","sex":"unisex","image_url":"https://cdn2.randewoo.ru/img/489949/n/1","properties":{"perfume_type":"eau de parfum","family":["amber","woody"],"upper_notes":["bergamot","peach","sage"],"core_notes":["aquatic notes","lily of the valley","orange"],"base_notes":["cedar","musk","vetiver"],"upper_tags":["airy","cool","light","bright","fresh"],"core_tags":["cool","fresh","bright","airy","light"],"base_tags":["mysterious","energetic","mossy","rich","dense","floral","earthy","warm"],"upper_characteristics":{"density":0.15,"earthiness":0.15,"floralcy":0.15,"freshness":0.3833333333333333,"fruityness":0.3833333333333333,"powderiness":0.15,"spiciness":0.15,"sweetness":0.15,"warmth":0.15,"woodiness":0.15},"core_characteristics":{"density":0.15,"earthiness":0.15,"floralcy":0.3833333333333333,"freshness":0.15,"fruityness":0.15,"powderiness":0.15,"spiciness":0.15,"sweetness":0.15,"warmth":0.15,"woodiness":0.15},"base_characteristics":{"density":0.15,"earthiness":0.3833333333333333,"floralcy":0.15,"freshness":0.15,"fruityness":0.15,"powderiness":0.3833333333333333,"spiciness":0.15,"sweetness":0.15,"warmth":0.15,"woodiness":0.3833333333333333}},"shops":[{"shop_name":"Randewoo","domain":"https://randewoo.ru","variants":[{"volume":100,"link":"https://randewoo.ru/product/helix?source_category=6\u0026preferred=489949","price":14516},{"volume":8,"link":"https://randewoo.ru/product/helix?source_category=6\u0026preferred=489949","price":1463},{"volume":50,"link":"https://randewoo.ru/product/helix?source_category=6\u0026preferred=489949","price":11636}]}]},"rank":4,"similarity_score":0.6572164309640512}]},{"input":{"brand":"Abercrombie \u0026 Fitch","name":"Authentic Self Man","sex":"male","image_url":"https://cdn2.randewoo.ru/img/443688/n/1","properties":{"perfume_type":"eau de toilette","family":[],"upper_notes":["cardamom","cypress","ginger"],"core_notes":["geranium"],"base_notes":["cedar","vanilla"],"upper_tags":["vanillic","clean","bright","dense","floral","energetic","resinous","mossy","sharp","marine","rich"],"core_tags":["light","romantic","bright","cool","resinous","elegant","marine","calm","clean","soft","fresh","dry","velvety","airy","sensual","fruity"],"base_tags":["warm","mysterious","energetic","rich","calm","dense"],"upper_characteristics":{"density":0.15,"earthiness":0.15,"floralcy":0.15,"freshness":0.15,"fruityness":0.15,"powderiness":0.15,"spiciness":0.6166666666666667,"sweetness":0.15,"warmth":0.15,"woodiness":0.15},"core_characteristics":{"density":0.15,"earthiness":0.15,"floralcy":0.15,"freshness":0.15,"fruityness":0.15,"powderiness":0.15,"spiciness":0.15,"sweetness":0.15,"warmth":0.15,"woodiness":0.15},"base_characteristics":{"density":0.15,"earthiness":0.15,"floralcy":0.15,"freshness":0.15,"fruityness":0.15,"powderiness":0.15,"spiciness":0.15,"sweetness":0.5,"warmth":0.5,"woodiness":0.5}},"shops":[{"shop_name":"Randewoo","domain":"https://randewoo.ru","variants":[{"volume":30,"link":"https://randewoo.ru/product/authentic-self-man?source_category=6\u0026preferred=443688","price":4091}]}]},"suggestions":[{"perfume":{"brand":"Laura Biagiotti","name":"Roma Uomo","sex":"male","image_url":"https://cdn2.randewoo.ru/img/12715/n/1","properties":{"perfume_type":"eau de toilette","family":["fresh","woody"],"upper_notes":["bay"],"core_notes":["geranium"],"base_notes":["coumarin","vanilla"],"upper_tags":["mossy","floral","resinous","marine","dense","bright","sharp","energetic","clean","vanillic","rich"],"core_tags":["fruity","romantic","light","marine","calm","resinous","elegant","cool","sensual","clean","soft","velvety","bright","airy","dry","fresh"],"base_tags":["dense","powdery","energetic","light","warm","sensual","mysterious","romantic","dry","caramel","velvety","cozy","soft","sweet","rich"],"upper_characteristics":{"density":0.15,"earthiness":0.15,"floralcy":0.15,"freshness":0.15,"fruityness":0.15,"powderiness":0.15,"spiciness":0.15,"sweetness":0.15,"warmth":0.15,"woodiness":0.15},"core_characteristics":{"density":0.15,"earthiness":0.15,"floralcy":0.15,"freshness":0.15,"fruityness":0.15,"powderiness":0.15,"spiciness":0.15,"sweetness":0.15,"warmth":0.15,"woodiness":0.15},"base_characteristics":{"density":0.15,"earthiness":0.15,"floralcy":0.15,"freshness":0.15,"fruityness":0.15,"powderiness":0.15,"spiciness":0.15,"sweetness":0.5,"warmth":0.5,"woodiness":0.15}},"shops":[{"shop_name":"Randewoo","domain":"https://randewoo.ru","variants":[{"volume":75,"link":"https://randewoo.ru/product/laura-biagiotti-roma-uomo?source_category=6\u0026preferred=12715","price":5780}]}]},"rank":1,"similarity_score":0.6619414109164236},{"perfume":{"brand":"Laura Biagiotti","name":"Essenza Di Roma Uomo","sex":"male","image_url":"https://cdn2.randewoo.ru/img/46206/n/1","properties":{"perfume_type":"eau de toilette","family":["fresh","woody"],"upper_notes":["bay"],"core_notes":["geranium"],"base_notes":["coumarin","vanilla"],"upper_tags":["rich","floral","energetic","clean","marine","resinous","vanillic","bright","sharp","dense","mossy"],"core_tags":["cool","marine","airy","light","sensual","soft","clean","resinous","fruity","calm","bright","dry","romantic","elegant","velvety","fresh"],"base_tags":["sensual","mysterious","romantic","light","cozy","dry","velvety","energetic","caramel","warm","dense","soft","rich","powdery","sweet"],"upper_characteristics":{"density":0.15,"earthiness":0.15,"floralcy":0.15,"freshness":0.15,"fruityness":0.15,"powderiness":0.15,"spiciness":0.15,"sweetness":0.15,"warmth":0.15,"woodiness":0.15},"core_characteristics":{"density":0.15,"earthiness":0.15,"floralcy":0.15,"freshness":0.15,"fruityness":0.15,"powderiness":0.15,"spiciness":0.15,"sweetness":0.15,"warmth":0.15,"woodiness":0.15},"base_characteristics":{"density":0.15,"earthiness":0.15,"floralcy":0.15,"freshness":0.15,"fruityness":0.15,"powderiness":0.15,"spiciness":0.15,"sweetness":0.5,"warmth":0.5,"woodiness":0.15}},"shops":[{"shop_name":"Randewoo","domain":"https://randewoo.ru","variants":[{"volume":125,"link":"https://randewoo.ru/product/laura-biagiotti-essenza-di-roma-uomo?source_category=6\u0026preferred=46206","price":12262}]}]},"rank":2,"similarity_score":0.6619414109164234},{"perfume":{"brand":"Roberto Cavalli","name":"Imperial Hyacinth","sex":"unisex","image_url":"https://cdn2.randewoo.ru/img/193040/n/1","properties":{"perfume_type":"eau de parfum","family":["amber","floral"],"upper_notes":["bergamot","cardamom","saffron"],"core_notes":["hyacinth","petalia"],"base_notes":["cedar","musk","vanilla"],"upper_tags":["clean","bright","mossy","resinous","vanillic","dense","energetic","floral","sharp","marine","rich"],"core_tags":["bright","light","dry","sensual","soft","cool","resinous","fresh","energetic","marine","clean","romantic","fruity","invigorating","airy","calm","elegant","velvety"],"base_tags":["rich","dense","mysterious","energetic","warm"],"upper_characteristics":{"density":0.15,"earthiness":0.15,"floralcy":0.15,"freshness":0.3833333333333333,"fruityness":0.15,"powderiness":0.15,"spiciness":0.3833333333333333,"sweetness":0.15,"warmth":0.15,"woodiness":0.15},"core_characteristics":{"density":0.15,"earthiness":0.15,"floralcy":0.15,"freshness":0.15,"fruityness":0.15,"powderiness":0.15,"spiciness":0.15,"sweetness":0.15,"warmth":0.15,"woodiness":0.15},"base_characteristics":{"density":0.15,"earthiness":0.15,"floralcy":0.15,"freshness":0.15,"fruityness":0.15,"powderiness":0.3833333333333333,"spiciness":0.15,"sweetness":0.3833333333333333,"warmth":0.3833333333333333,"woodiness":0.3833333333333333}},"shops":[{"shop_name":"Randewoo","domain":"https://randewoo.ru","variants":[{"volume":100,"link":"https://randewoo.ru/product/roberto-cavalli-imperial-hyacinth?source_category=6\u0026preferred=193040","price":11636}]}]},"rank":3,"similarity_score":0.6618393103275753},{"perfume":{"brand":"Asgharali","name":"Step Up","sex":"unisex","image_url":"https://cdn2.randewoo.ru/img/254842/n/1","properties":{"perfume_type":"eau de parfum","family":["amber","fresh"],"upper_notes":["bergamot","cinnamon","pepper"],"core_notes":["geranium"],"base_notes":["amber","musk","vanilla"],"upper_tags":["marine","bright","energetic","vanillic","fresh","sharp","dense","cold","rich"],"core_tags":["light","elegant","calm","dry","cool","fresh","soft","romantic","clean","airy","fruity","sensual","bright","resinous","velvety","marine"],"base_tags":["energetic","warm","dense","cozy","mysterious","rich","dry"],"upper_characteristics":{"density":0.15,"earthiness":0.15,"floralcy":0.15,"freshness":0.3833333333333333,"fruityness":0.15,"powderiness":0.15,"spiciness":0.6166666666666667,"sweetness":0.15,"warmth":0.15,"woodiness":0.15},"core_characteristics":{"density":0.15,"earthiness":0.15,"floralcy":0.15,"freshness":0.15,"fruityness":0.15,"powderiness":0.15,"spiciness":0.15,"sweetness":0.15,"warmth":0.15,"woodiness":0.15},"base_characteristics":{"density":0.3833333333333333,"earthiness":0.15,"floralcy":0.15,"freshness":0.15,"fruityness":0.15,"powderiness":0.3833333333333333,"spiciness":0.15,"sweetness":0.3833333333333333,"warmth":0.6166666666666667,"woodiness":0.15}},"shops":[{"shop_name":"Randewoo","domain":"https://randewoo.ru","variants":[{"volume":50,"link":"https://randewoo.ru/product/asgharali-step-up?source_category=6\u0026preferred=254842","price":0}]}]},"rank":4,"similarity_score":0.654489824005228}]},{"input":{"brand":"Adidas","name":"UEFA Champions League Champions Intense","sex":"male","image_url":"https://cdn2.randewoo.ru/img/426918/n/1","properties":{"perfume_type":"eau de parfum","family":["fresh"],"upper_notes":["lavender","lemon"],"core_notes":["apple"],"base_notes":["moss","patchouli","vanilla"],"upper_tags":["airy","light","marine","bright","fresh","sharp","cool"],"core_tags":["elegant","cool","sweet","invigorating","light","fresh","powdery","soft","energetic","dry","airy","salty","bitter","romantic","green","bright","sensual"],"base_tags":["mossy","invigorating","sensual","energetic","warm","rich","romantic","dense","mysterious"],"upper_characteristics":{"density":0.15,"earthiness":0.15,"floralcy":0.15,"freshness":0.5,"fruityness":0.15,"powderiness":0.15,"spiciness":0.15,"sweetness":0.15,"warmth":0.15,"woodiness":0.15},"core_characteristics":{"density":0.15,"earthiness":0.15,"floralcy":0.15,"freshness":0.15,"fruityness":0.85,"powderiness":0.15,"spiciness":0.15,"sweetness":0.15,"warmth":0.15,"woodiness":0.15},"base_characteristics":{"density":0.15,"earthiness":0.6166666666666666,"floralcy":0.15,"freshness":0.15,"fruityness":0.15,"powderiness":0.15,"spiciness":0.15,"sweetness":0.3833333333333333,"warmth":0.3833333333333333,"woodiness":0.15}},"shops":[{"shop_name":"Randewoo","domain":"https://randewoo.ru","variants":[{"volume":100,"link":"https://randewoo.ru/product/uefa-champions-league-champions-intense?source_category=6\u0026preferred=426918","price":0}]}]},"suggestions":[{"perfume":{"brand":"Mont Blanc","name":"Patchouli Ink","sex":"unisex","image_url":"https://cdn2.randewoo.ru/img/488139/n/1","properties":{"perfume_type":"eau de parfum","family":["woody"],"upper_notes":["bergamot"],"core_notes":["blueberry"],"base_notes":["patchouli","vanilla"],"upper_tags":["cool","marine","noble","bright","light","bold","sharp","fresh","salty","invigorating","cold","airy"],"core_tags":["rich","bright","sensual","fresh","light","energetic","elegant","green","dry","romantic","powdery","salty","soft","bitter","cool","sweet"],"base_tags":["energetic","dense","rich","romantic","mysterious","invigorating","warm","sensual"],"upper_characteristics":{"density":0.15,"earthiness":0.15,"floralcy":0.15,"freshness":0.85,"fruityness":0.15,"powderiness":0.15,"spiciness":0.15,"sweetness":0.15,"warmth":0.15,"woodiness":0.15},"core_characteristics":{"density":0.15,"earthiness":0.15,"floralcy":0.15,"freshness":0.15,"fruityness":0.85,"powderiness":0.15,"spiciness":0.15,"sweetness":0.15,"warmth":0.15,"woodiness":0.15},"base_characteristics":{"density":0.15,"earthiness":0.5,"floralcy":0.15,"freshness":0.15,"fruityness":0.15,"powderiness":0.15,"spiciness":0.15,"sweetness":0.5,"warmth":0.5,"woodiness":0.15}},"shops":[{"shop_name":"Randewoo","domain":"https://randewoo.ru","variants":[{"volume":125,"link":"https://randewoo.ru/product/patchouli-ink?source_category=6\u0026preferred=488139","price":14171}]}]},"rank":1,"similarity_score":0.6694834909627284},{"perfume":{"brand":"DILIS","name":"Seduisant","sex":"male","image_url":"https://pcdn.goldapple.ru/p/p/19000390678/imgmain_11db3652a5dc4a1fbd03aa5a2afd11b5.jpg","properties":{"perfume_type":"eau de parfum","family":["fresh","woody"],"upper_notes":["citrus","lavender","nootka"],"core_notes":["apple","geranium"],"base_notes":["bohea","patchouli","tonka beans"],"upper_tags":["energetic","sharp","airy","cool","light","fresh","marine","bright","resinous"],"core_tags":["romantic","elegant","soft","light","dry","cool","sensual","airy","bright","fresh"],"base_tags":["romantic","sensual","mysterious","warm","rich","dense","energetic"],"upper_characteristics":{"density":0.15,"earthiness":0.15,"floralcy":0.15,"freshness":0.3833333333333333,"fruityness":0.15,"powderiness":0.15,"spiciness":0.15,"sweetness":0.15,"warmth":0.15,"woodiness":0.15},"core_characteristics":{"density":0.15,"earthiness":0.15,"floralcy":0.15,"freshness":0.15,"fruityness":0.5,"powderiness":0.15,"spiciness":0.15,"sweetness":0.15,"warmth":0.15,"woodiness":0.15},"base_characteristics":{"density":0.15,"earthiness":0.3833333333333333,"floralcy":0.15,"freshness":0.15,"fruityness":0.15,"powderiness":0.15,"spiciness":0.15,"sweetness":0.15,"warmth":0.3833333333333333,"woodiness":0.15}},"shops":[{"shop_name":"Gold Apple","domain":"https://goldapple.ru","variants":[{"volume":100,"link":"https://goldapple.ru/19000390678-seduisant","price":2505}]}]},"rank":2,"similarity_score":0.6591898218701836},{"perfume":{"brand":"Signature","name":"Jade","sex":"unisex","image_url":"https://cdn2.randewoo.ru/img/230559/n/1","properties":{"perfume_type":"набор (п/вода","family":["amber"],"upper_notes":["bergamot","lemon","orange"],"core_notes":["fruity"],"base_notes":["amber","musk","vanilla"],"upper_tags":["invigorating","airy","fresh","cool","light","salty","bright"],"core_tags":["light","invigorating","salty","soft","airy","energetic","cool","sweet","bitter","green","romantic","sensual","fresh","powdery","dry","elegant","bright"],"base_tags":["cozy","mysterious","warm","dry","energetic","dense","rich"],"upper_characteristics":{"density":0.15,"earthiness":0.15,"floralcy":0.15,"freshness":0.6166666666666666,"fruityness":0.15,"powderiness":0.15,"spiciness":0.15,"sweetness":0.15,"warmth":0.15,"woodiness":0.15},"core_characteristics":{"density":0.15,"earthiness":0.15,"floralcy":0.15,"freshness":0.15,"fruityness":0.85,"powderiness":0.15,"spiciness":0.15,"sweetness":0.15,"warmth":0.15,"woodiness":0.15},"base_characteristics":{"density":0.3833333333333333,"earthiness":0.15,"floralcy":0.15,"freshness":0.15,"fruityness":0.15,"powderiness":0.3833333333333333,"spiciness":0.15,"sweetness":0.3833333333333333,"warmth":0.6166666666666667,"woodiness":0.15}},"shops":[]},"rank":3,"similarity_score":0.6561789068056221},{"perfume":{"brand":"BOULEVARD","name":"GRANDS BOULEVARDS","sex":"male","image_url":"https://pcdn.goldapple.ru/p/p/19000306778/imgmain_6489b60bfadf4944b0baeb9288c9f25e.jpg","properties":{"perfume_type":"eau de parfum","family":["fresh"],"upper_notes":["bergamot","lemon","orange"],"core_notes":["fruity"],"base_notes":["amber","musk","vanilla"],"upper_tags":["bright","airy","fresh","invigorating","cool","light","salty"],"core_tags":["salty","sensual","cool","green","light","sweet","bright","airy","romantic","fresh","powdery","energetic","soft","invigorating","bitter","elegant","dry"],"base_tags":["dense","dry","energetic","cozy","mysterious","warm","rich"],"upper_characteristics":{"density":0.15,"earthiness":0.15,"floralcy":0.15,"freshness":0.6166666666666666,"fruityness":0.15,"powderiness":0.15,"spiciness":0.15,"sweetness":0.15,"warmth":0.15,"woodiness":0.15},"core_characteristics":{"density":0.15,"earthiness":0.15,"floralcy":0.15,"freshness":0.15,"fruityness":0.85,"powderiness":0.15,"spiciness":0.15,"sweetness":0.15,"warmth":0.15,"woodiness":0.15},"base_characteristics":{"density":0.3833333333333333,"earthiness":0.15,"floralcy":0.15,"freshness":0.15,"fruityness":0.15,"powderiness":0.3833333333333333,"spiciness":0.15,"sweetness":0.3833333333333333,"warmth":0.6166666666666667,"woodiness":0.15}},"shops":[{"shop_name":"Gold Apple","domain":"https://goldapple.ru","variants":[{"volume":100,"link":"https://goldapple.ru/19000306778-grands-boulevards","price":3890}]}]},"rank":4,"similarity_score":0.6561789068056221}]},{"input":{"brand":"100BON","name":"Ambre Sensuel","sex":"unisex","image_url":"https://pcdn.goldapple.ru/p/p/19000159052/imgmain.jpg","properties":{"perfume_type":"eau de toilette","family":["amber","woody"],"upper_notes":["rose"],"core_notes":["amber"],"base_notes":["patchouli"],"upper_tags":["soft","energetic","airy","mysterious","fruity","sweet","calm","dense","cozy","elegant","resinous","caramel","sensual","light","clean","warm","romantic","dry","invigorating","rich"],"core_tags":["floral","soapy","warm","cozy","calm","dry","mysterious","rich","dense","energetic","mossy","earthy"],"base_tags":["energetic","fruity","invigorating","earthy","leathery","warm","bold","dense","romantic","sensual","clean","floral","woody","rich","mysterious","mossy"],"upper_characteristics":{"density":0.15,"earthiness":0.15,"floralcy":0.85,"freshness":0.15,"fruityness":0.15,"powderiness":0.15,"spiciness":0.15,"sweetness":0.15,"warmth":0.15,"woodiness":0.15},"core_characteristics":{"density":0.85,"earthiness":0.15,"floralcy":0.15,"freshness":0.15,"fruityness":0.15,"powderiness":0.15,"spiciness":0.15,"sweetness":0.15,"warmth":0.85,"woodiness":0.15},"base_characteristics":{"density":0.15,"earthiness":0.85,"floralcy":0.15,"freshness":0.15,"fruityness":0.15,"powderiness":0.15,"spiciness":0.15,"sweetness":0.15,"warmth":0.15,"woodiness":0.15}},"shops":[{"shop_name":"Gold Apple","domain":"https://goldapple.ru","variants":[{"volume":50,"link":"https://goldapple.ru/19000159052-ambre-sensuel","price":5150}]}]},"suggestions":[{"perfume":{"brand":"Boadicea The Victorious","name":"Salubrious","sex":"unisex","image_url":"https://cdn2.randewoo.ru/img/30906/n/1","properties":{"perfume_type":"eau de parfum","family":["amber","floral"],"upper_notes":["geranium","orange","rose"],"core_notes":["amber"],"base_notes":["incienso","patchouli","vetiver"],"upper_tags":["airy","dry","romantic","light","soft","sensual","elegant"],"core_tags":["mossy","dense","earthy","soapy","energetic","warm","floral","calm","mysterious","dry","cozy","rich"],"base_tags":["energetic","mysterious","earthy","warm","rich","dense","mossy","floral"],"upper_characteristics":{"density":0.15,"earthiness":0.15,"floralcy":0.3833333333333333,"freshness":0.15,"fruityness":0.15,"powderiness":0.15,"spiciness":0.15,"sweetness":0.15,"warmth":0.15,"woodiness":0.15},"core_characteristics":{"density":0.85,"earthiness":0.15,"floralcy":0.15,"freshness":0.15,"fruityness":0.15,"powderiness":0.15,"spiciness":0.15,"sweetness":0.15,"warmth":0.85,"woodiness":0.15},"base_characteristics":{"density":0.15,"earthiness":0.6166666666666667,"floralcy":0.15,"freshness":0.15,"fruityness":0.15,"powderiness":0.15,"spiciness":0.15,"sweetness":0.15,"warmth":0.15,"woodiness":0.15}},"shops":[{"shop_name":"Randewoo","domain":"https://randewoo.ru","variants":[{"volume":100,"link":"https://randewoo.ru/product/boadicea-the-victorious-salubrious?source_category=6\u0026preferred=30906","price":0}]}]},"rank":1,"similarity_score":0.6787441143340126},{"perfume":{"brand":"Bohoboco","name":"Yellow Rose Incense","sex":"unisex","image_url":"https://cdn2.randewoo.ru/img/444196/n/1","properties":{"perfume_type":"parfum","family":["amber","floral","woody"],"upper_notes":["cinnamon","dianthus","rose"],"core_notes":["amber","incienso","oud"],"base_notes":["benzoin","patchouli"],"upper_tags":["dry"],"core_tags":["mossy","mysterious","calm","warm","dense","dry","earthy","rich","energetic","floral","soapy","cozy"],"base_tags":["warm","energetic","dense","floral","clean","rich","mysterious","invigorating","romantic","earthy","sensual","mossy"],"upper_characteristics":{"density":0.15,"earthiness":0.15,"floralcy":0.3833333333333333,"freshness":0.15,"fruityness":0.15,"powderiness":0.15,"spiciness":0.3833333333333333,"sweetness":0.15,"warmth":0.15,"woodiness":0.15},"core_characteristics":{"density":0.6166666666666667,"earthiness":0.15,"floralcy":0.15,"freshness":0.15,"fruityness":0.15,"powderiness":0.15,"spiciness":0.15,"sweetness":0.15,"warmth":0.3833333333333333,"woodiness":0.15},"base_characteristics":{"density":0.15,"earthiness":0.5,"floralcy":0.15,"freshness":0.15,"fruityness":0.15,"powderiness":0.15,"spiciness":0.15,"sweetness":0.15,"warmth":0.15,"woodiness":0.15}},"shops":[{"shop_name":"Randewoo","domain":"https://randewoo.ru","variants":[{"volume":50,"link":"https://randewoo.ru/product/yellow-rose-incense?source_category=6\u0026preferred=444196","price":12297}]}]},"rank":2,"similarity_score":0.6613930128137034},{"perfume":{"brand":"Zielinski \u0026 Rozen","name":"Amber, Patchouli","sex":"unisex","image_url":"https://pcdn.goldapple.ru/p/p/19000021493/imgmain_cbb9c38ecaa84a45b88798dbc432f62f.jpg","properties":{"perfume_type":"parfum","family":["woody"],"upper_notes":["tobacco"],"core_notes":["amber"],"base_notes":["patchouli"],"upper_tags":["rich","warm","mossy","fruity","earthy","romantic","invigorating","energetic","clean","sensual","dense","soapy","bold","woody","floral","mysterious"],"core_tags":["rich","energetic","floral","earthy","mossy","dry","warm","mysterious","calm","dense","cozy","soapy"],"base_tags":["dense","mossy","rich","clean","fruity","bold","woody","mysterious","romantic","sensual","invigorating","energetic","leathery","warm","earthy","floral"],"upper_characteristics":{"density":0.15,"earthiness":0.15,"floralcy":0.15,"freshness":0.15,"fruityness":0.15,"powderiness":0.15,"spiciness":0.15,"sweetness":0.15,"warmth":0.15,"woodiness":0.15},"core_characteristics":{"density":0.85,"earthiness":0.15,"floralcy":0.15,"freshness":0.15,"fruityness":0.15,"powderiness":0.15,"spiciness":0.15,"sweetness":0.15,"warmth":0.85,"woodiness":0.15},"base_characteristics":{"density":0.15,"earthiness":0.85,"floralcy":0.15,"freshness":0.15,"fruityness":0.15,"powderiness":0.15,"spiciness":0.15,"sweetness":0.15,"warmth":0.15,"woodiness":0.15}},"shops":[{"shop_name":"Gold Apple","domain":"https://goldapple.ru","variants":[{"volume":50,"link":"https://goldapple.ru/90151200001-moss","price":7350},{"volume":10,"link":"https://goldapple.ru/19000021493-moss","price":2690}]}]},"rank":3,"similarity_score":0.6610920191489577},{"perfume":{"brand":"Zielinski \u0026 Rozen","name":"tobacco, amber, patchouli","sex":"unisex","image_url":"https://pcdn.goldapple.ru/p/p/19000084111/imgmain_8c223112f35f4bd397bbf171020d2cab.jpg","properties":{"perfume_type":"parfum","family":["amber"],"upper_notes":["tobacco"],"core_notes":["amber"],"base_notes":["patchouli"],"upper_tags":["rich","fruity","floral","clean","earthy","sensual","woody","dense","energetic","mysterious","soapy","romantic","mossy","warm","bold","invigorating"],"core_tags":["dry","mossy","cozy","warm","dense","earthy","soapy","floral","energetic","mysterious","calm","rich"],"base_tags":["energetic","mysterious","invigorating","rich","mossy","dense","floral","romantic","sensual","bold","woody","earthy","clean","leathery","fruity","warm"],"upper_characteristics":{"density":0.15,"earthiness":0.15,"floralcy":0.15,"freshness":0.15,"fruityness":0.15,"powderiness":0.15,"spiciness":0.15,"sweetness":0.15,"warmth":0.15,"woodiness":0.15},"core_characteristics":{"density":0.85,"earthiness":0.15,"floralcy":0.15,"freshness":0.15,"fruityness":0.15,"powderiness":0.15,"spiciness":0.15,"sweetness":0.15,"warmth":0.85,"woodiness":0.15},"base_characteristics":{"density":0.15,"earthiness":0.85,"floralcy":0.15,"freshness":0.15,"fruityness":0.15,"powderiness":0.15,"spiciness":0.15,"sweetness":0.15,"warmth":0.15,"woodiness":0.15}},"shops":[{"shop_name":"Gold Apple","domain":"https://goldapple.ru","variants":[{"volume":10,"link":"https://goldapple.ru/19000084110-tobacco-amber-patchouli","price":2690},{"volume":50,"link":"https://goldapple.ru/19000084111-tobacco-amber-patchouli","price":7350}]}]},"rank":4,"similarity_score":0.6610920191489575}]},{"input":{"brand":"Versace","name":"Versus Uomo","sex":"male","image_url":"https://cdn2.randewoo.ru/img/20643/n/1","properties":{"perfume_type":"eau de toilette","family":["amber","woody"],"upper_notes":["bergamot","lavender","lemon","lime","peach","tangerine"],"core_notes":["bark","coriander","dianthus","jasmine"],"base_notes":["benzoin","cedar","indian spices","musk","sandalwood"],"upper_tags":["light","bright","cool","airy","sharp","marine","invigorating","fresh","salty"],"core_tags":["resinous"],"base_tags":["mysterious","mossy","resinous","energetic","rich","floral","dense","warm","earthy"],"upper_characteristics":{"density":0.15,"earthiness":0.15,"floralcy":0.15,"freshness":0.5,"fruityness":0.26666666666666666,"powderiness":0.15,"spiciness":0.15,"sweetness":0.15,"warmth":0.15,"woodiness":0.15},"core_characteristics":{"density":0.15,"earthiness":0.15,"floralcy":0.32499999999999996,"freshness":0.15,"fruityness":0.15,"powderiness":0.15,"spiciness":0.15,"sweetness":0.15,"warmth":0.15,"woodiness":0.15},"base_characteristics":{"density":0.15,"earthiness":0.15,"floralcy":0.15,"freshness":0.15,"fruityness":0.15,"powderiness":0.2899999999999999,"spiciness":0.2899999999999999,"sweetness":0.15,"warmth":0.2899999999999999,"woodiness":0.43}},"shops":[{"shop_name":"Randewoo","domain":"https://randewoo.ru","variants":[{"volume":100,"link":"https://randewoo.ru/product/versace-versus-uomo?source_category=6\u0026preferred=20643","price":35647}]}]},"suggestions":[{"perfume":{"brand":"Azzaro","name":"Chrome","sex":"male","image_url":"https://cdn2.randewoo.ru/img/17776/n/1","properties":{"perfume_type":"eau de toilette","family":["fresh"],"upper_notes":["bergamot","lemon","neroli","pineapple","rosemary"],"core_notes":["coriander","cyclamen","jasmine","oakmoss"],"base_notes":["cardamom","cedar","musk","oakmoss","sandalwood"],"upper_tags":["fresh","cool","invigorating","light","marine","bright","airy"],"core_tags":["resinous"],"base_tags":["warm","dense","mysterious","rich","clean","resinous","energetic","mossy","earthy","floral"],"upper_characteristics":{"density":0.15,"earthiness":0.15,"floralcy":0.29,"freshness":0.43,"fruityness":0.2899999999999999,"powderiness":0.15,"spiciness":0.15,"sweetness":0.15,"warmth":0.15,"woodiness":0.2899999999999999},"core_characteristics":{"density":0.15,"earthiness":0.32499999999999996,"floralcy":0.32499999999999996,"freshness":0.15,"fruityness":0.15,"powderiness":0.15,"spiciness":0.15,"sweetness":0.15,"warmth":0.15,"woodiness":0.32499999999999996},"base_characteristics":{"density":0.15,"earthiness":0.2899999999999999,"floralcy":0.15,"freshness":0.15,"fruityness":0.15,"powderiness":0.2899999999999999,"spiciness":0.2899999999999999,"sweetness":0.15,"warmth":0.15,"woodiness":0.5700000000000001}},"shops":[{"shop_name":"Randewoo","domain":"https://randewoo.ru","variants":[{"volume":100,"link":"https://randewoo.ru/product/azzaro-chrome?source_category=6\u0026preferred=17776","price":4689},{"volume":8,"link":"https://randewoo.ru/product/azzaro-chrome?source_category=6\u0026preferred=17776","price":787},{"volume":30,"link":"https://randewoo.ru/product/azzaro-chrome?source_category=6\u0026preferred=17776","price":3884},{"volume":200,"link":"https://randewoo.ru/product/azzaro-chrome?source_category=6\u0026preferred=17776","price":6814}]}]},"rank":1,"similarity_score":0.6767540103288291},{"perfume":{"brand":"Comporta Perfumes","name":"Mosquito Man Extrait De Parfum","sex":"male","image_url":"https://cdn2.randewoo.ru/img/458755/n/1","properties":{"perfume_type":"parfum","family":["floral","fresh"],"upper_notes":["bergamot","citrus","galbanum","tangerine"],"core_notes":["bark","lily of the valley","syringa"],"base_notes":["cedar","musk","sandalwood"],"upper_tags":["invigorating","cold","airy","cool","sharp","bright","fresh","light","marine","salty"],"core_tags":["airy","clean","energetic","sensual","resinous","romantic"],"base_tags":["floral","energetic","earthy","rich","warm","dense","mossy","mysterious"],"upper_characteristics":{"density":0.15,"earthiness":0.15,"floralcy":0.15,"freshness":0.49999999999999994,"fruityness":0.15,"powderiness":0.15,"spiciness":0.15,"sweetness":0.15,"warmth":0.15,"woodiness":0.15},"core_characteristics":{"density":0.15,"earthiness":0.15,"floralcy":0.3833333333333333,"freshness":0.15,"fruityness":0.15,"powderiness":0.15,"spiciness":0.15,"sweetness":0.15,"warmth":0.15,"woodiness":0.15},"base_characteristics":{"density":0.15,"earthiness":0.15,"floralcy":0.15,"freshness":0.15,"fruityness":0.15,"powderiness":0.3833333333333333,"spiciness":0.15,"sweetness":0.15,"warmth":0.15,"woodiness":0.6166666666666667}},"shops":[{"shop_name":"Randewoo","domain":"https://randewoo.ru","variants":[{"volume":100,"link":"https://randewoo.ru/product/mosquito-man-extrait-de-parfum?source_category=6\u0026preferred=458755","price":0}]}]},"rank":2,"similarity_score":0.6766396881097774},{"perfume":{"brand":"Chris Collins","name":"Autumn Rhythm","sex":"unisex","image_url":"https://cdn2.randewoo.ru/img/394503/n/1","properties":{"perfume_type":"parfum","family":["woody"],"upper_notes":["bergamot"],"core_notes":["bark","lily of the valley","tea"],"base_notes":["ambrette","cedar","musk","skin"],"upper_tags":["airy","bold","marine","cold","noble","sharp","bright","cool","light","fresh","salty","invigorating"],"core_tags":["airy","energetic","resinous"],"base_tags":["velvety","energetic","mossy","rich","floral","warm","mysterious","soft","earthy","dense","dry"],"upper_characteristics":{"density":0.15,"earthiness":0.15,"floralcy":0.15,"freshness":0.85,"fruityness":0.15,"powderiness":0.15,"spiciness":0.15,"sweetness":0.15,"warmth":0.15,"woodiness":0.15},"core_characteristics":{"density":0.15,"earthiness":0.15,"floralcy":0.3833333333333333,"freshness":0.15,"fruityness":0.15,"powderiness":0.15,"spiciness":0.15,"sweetness":0.15,"warmth":0.15,"woodiness":0.15},"base_characteristics":{"density":0.15,"earthiness":0.15,"floralcy":0.15,"freshness":0.15,"fruityness":0.15,"powderiness":0.32499999999999996,"spiciness":0.15,"sweetness":0.15,"warmth":0.15,"woodiness":0.32499999999999996}},"shops":[{"shop_name":"Randewoo","domain":"https://randewoo.ru","variants":[{"volume":50,"link":"https://randewoo.ru/product/autumn-rhythm?source_category=6\u0026preferred=394503","price":0}]}]},"rank":3,"similarity_score":0.6736796612873474},{"perfume":{"brand":"Ferrari","name":"Scuderia Ferrari Red","sex":"male","image_url":"https://cdn2.randewoo.ru/img/181367/n/1","properties":{"perfume_type":"eau de toilette","family":["fresh"],"upper_notes":["bergamot","galbanum","mint","orange","petitgrain"],"core_notes":["bark","geranium","jasmine","nutmeg"],"base_notes":["cedar","moss","sandalwood","vanilla"],"upper_tags":["bright","airy","marine","sharp","invigorating","cool","fresh","light","cold"],"core_tags":["airy","resinous"],"base_tags":["rich","mossy","dense","warm","energetic","mysterious"],"upper_characteristics":{"density":0.15,"earthiness":0.15,"floralcy":0.15,"freshness":0.43,"fruityness":0.15,"powderiness":0.15,"spiciness":0.15,"sweetness":0.15,"warmth":0.15,"woodiness":0.15},"core_characteristics":{"density":0.15,"earthiness":0.15,"floralcy":0.32499999999999996,"freshness":0.15,"fruityness":0.15,"powderiness":0.15,"spiciness":0.15,"sweetness":0.15,"warmth":0.15,"woodiness":0.15},"base_characteristics":{"density":0.15,"earthiness":0.32499999999999996,"floralcy":0.15,"freshness":0.15,"fruityness":0.15,"powderiness":0.15,"spiciness":0.15,"sweetness":0.32499999999999996,"warmth":0.32499999999999996,"woodiness":0.5}},"shops":[{"shop_name":"Randewoo","domain":"https://randewoo.ru","variants":[{"volume":125,"link":"https://randewoo.ru/product/ferrari-scuderia-ferrari-red?source_category=6\u0026preferred=181367","price":4443}]}]},"rank":4,"similarity_score":0.6733654520984962}]},{"input":{"brand":"Aramis","name":"900","sex":"male","image_url":"https://cdn2.randewoo.ru/img/142239/n/1","properties":{"perfume_type":"eau de cologne","family":[],"upper_notes":["bergamot","coriander","lemon"],"core_notes":["dianthus","geranium","iris","jasmine","lily of the valley","rose"],"base_notes":["amber","civet","oakmoss","patchouli","sandalwood","vetiver"],"upper_tags":["airy","light","marine","cold","bright","bold","salty","noble","fresh","cool","invigorating","sharp"],"core_tags":["elegant","soft","dry","romantic","resinous","light","fruity","clean","sensual"],"base_tags":["dense","energetic","warm","floral","rich","mysterious","clean","earthy","sensual","romantic","mossy"],"upper_characteristics":{"density":0.15,"earthiness":0.15,"floralcy":0.15,"freshness":0.6166666666666667,"fruityness":0.15,"powderiness":0.15,"spiciness":0.15,"sweetness":0.15,"warmth":0.15,"woodiness":0.15},"core_characteristics":{"density":0.15,"earthiness":0.15,"floralcy":0.5,"freshness":0.15,"fruityness":0.15,"powderiness":0.2666666666666666,"spiciness":0.15,"sweetness":0.15,"warmth":0.15,"woodiness":0.15},"base_characteristics":{"density":0.2666666666666666,"earthiness":0.5,"floralcy":0.15,"freshness":0.15,"fruityness":0.15,"powderiness":0.15,"spiciness":0.15,"sweetness":0.15,"warmth":0.2666666666666666,"woodiness":0.3833333333333333}},"shops":[{"shop_name":"Randewoo","domain":"https://randewoo.ru","variants":[{"volume":100,"link":"https://randewoo.ru/product/aramis-900?source_category=6\u0026preferred=142239","price":31969}]}]},"suggestions":[{"perfume":{"brand":"Aramis","name":"900 Винтаж","sex":"male","image_url":"https://cdn2.randewoo.ru/img/35275/n/1","properties":{"perfume_type":"eau de cologne","family":["woody"],"upper_notes":["bergamot","coriander","lemon"],"core_notes":["bark","dianthus","geranium","jasmine","lily of the valley","rose"],"base_notes":["amber","civet","oakmoss","patchouli","sandalwood","vetiver"],"upper_tags":["light","noble","airy","cold","sharp","salty","fresh","cool","invigorating","bold","marine","bright"],"core_tags":["clean","sensual","romantic","resinous"],"base_tags":["warm","mossy","mysterious","clean","sensual","dense","earthy","energetic","rich","romantic","floral"],"upper_characteristics":{"density":0.15,"earthiness":0.15,"floralcy":0.15,"freshness":0.6166666666666667,"fruityness":0.15,"powderiness":0.15,"spiciness":0.15,"sweetness":0.15,"warmth":0.15,"woodiness":0.15},"core_characteristics":{"density":0.15,"earthiness":0.15,"floralcy":0.5,"freshness":0.15,"fruityness":0.15,"powderiness":0.15,"spiciness":0.15,"sweetness":0.15,"warmth":0.15,"woodiness":0.15},"base_characteristics":{"density":0.2666666666666666,"earthiness":0.5,"floralcy":0.15,"freshness":0.15,"fruityness":0.15,"powderiness":0.15,"spiciness":0.15,"sweetness":0.15,"warmth":0.2666666666666666,"woodiness":0.3833333333333333}},"shops":[{"shop_name":"Randewoo","domain":"https://randewoo.ru","variants":[{"volume":100,"link":"https://randewoo.ru/product/aramis-900-vintazh?source_category=6\u0026preferred=35275","price":31969}]}]},"rank":1,"similarity_score":0.6949911283047934},{"perfume":{"brand":"Gucci","name":"Nobile","sex":"male","image_url":"https://cdn2.randewoo.ru/img/24298/n/1","properties":{"perfume_type":"eau de toilette","family":["fresh"],"upper_notes":["bergamot","lavender","lemon","nutmeg","rosemary","tarragon"],"core_notes":["cyclamen","dianthus","geranium","jasmine","rose"],"base_notes":["amber","musk","oakmoss","patchouli","sandalwood","vetiver"],"upper_tags":["fresh","resinous","bright","cool","airy","sharp","elegant","light","energetic","marine"],"core_tags":["romantic","fruity","dry","resinous","clean","soft","elegant","sensual","light"],"base_tags":["rich","floral","mossy","energetic","warm","sensual","clean","leathery","romantic","mysterious","earthy","dense"],"upper_characteristics":{"density":0.15,"earthiness":0.15,"floralcy":0.26666666666666666,"freshness":0.3833333333333333,"fruityness":0.15,"powderiness":0.15,"spiciness":0.15,"sweetness":0.15,"warmth":0.15,"woodiness":0.15},"core_characteristics":{"density":0.15,"earthiness":0.15,"floralcy":0.43,"freshness":0.15,"fruityness":0.15,"powderiness":0.15,"spiciness":0.15,"sweetness":0.15,"warmth":0.15,"woodiness":0.15},"base_characteristics":{"density":0.2666666666666666,"earthiness":0.5,"floralcy":0.15,"freshness":0.15,"fruityness":0.15,"powderiness":0.2666666666666666,"spiciness":0.15,"sweetness":0.15,"warmth":0.2666666666666666,"woodiness":0.3833333333333333}},"shops":[{"shop_name":"Randewoo","domain":"https://randewoo.ru","variants":[{"volume":120,"link":"https://randewoo.ru/product/gucci-nobile?source_category=6\u0026preferred=24298","price":83875},{"volume":30,"link":"https://randewoo.ru/product/gucci-nobile?source_category=6\u0026preferred=24298","price":16462}]}]},"rank":2,"similarity_score":0.6884547936013025},{"perfume":{"brand":"Shiseido","name":"Enchanting Dance","sex":"unisex","image_url":"https://cdn2.randewoo.ru/img/33190/n/1","properties":{"perfume_type":"parfum","family":["floral","woody"],"upper_notes":["bergamot","cardamom","lemon"],"core_notes":["dianthus","honey","iris","jasmine","lily of the valley","tuberose","ylang-ylang"],"base_notes":["benzoin","civet","incienso","oakmoss","patchouli","sandalwood","vetiver"],"upper_tags":["bright","salty","invigorating","cool","noble","marine","airy","light","fresh","sharp","bold","cold"],"core_tags":["soft","sensual","romantic","dry"],"base_tags":["romantic","earthy","floral","energetic","sensual","clean","warm","rich","mysterious","mossy","dense"],"upper_characteristics":{"density":0.15,"earthiness":0.15,"floralcy":0.15,"freshness":0.6166666666666667,"fruityness":0.15,"powderiness":0.15,"spiciness":0.3833333333333333,"sweetness":0.15,"warmth":0.15,"woodiness":0.15},"core_characteristics":{"density":0.15,"earthiness":0.15,"floralcy":0.55,"freshness":0.15,"fruityness":0.15,"powderiness":0.24999999999999994,"spiciness":0.15,"sweetness":0.24999999999999994,"warmth":0.15,"woodiness":0.15},"base_characteristics":{"density":0.15,"earthiness":0.45,"floralcy":0.15,"freshness":0.15,"fruityness":0.15,"powderiness":0.15,"spiciness":0.15,"sweetness":0.15,"warmth":0.15,"woodiness":0.35}},"shops":[{"shop_name":"Randewoo","domain":"https://randewoo.ru","variants":[{"volume":20,"link":"https://randewoo.ru/product/shiseido-enchanting-dance?source_category=6\u0026preferred=33190","price":48927}]}]},"rank":3,"similarity_score":0.6876017780452538},{"perfume":{"brand":"Loewe","name":"Pour Homme","sex":"male","image_url":"https://cdn2.randewoo.ru/img/55738/n/1","properties":{"perfume_type":"eau de toilette","family":["fresh"],"upper_notes":["basil","lavender","lemon"],"core_notes":["geranium","lily of the valley"],"base_notes":["amber","oakmoss","sandalwood","vetiver"],"upper_tags":["sharp","elegant","airy","cool","bright","cold","resinous","energetic","fresh","marine","light"],"core_tags":["romantic","fresh","clean","elegant","airy","velvety","resinous","fruity","bright","sensual","calm","light","cool","marine","soft","dry"],"base_tags":["energetic","mossy","mysterious","floral","dense","warm","rich","earthy"],"upper_characteristics":{"density":0.15,"earthiness":0.15,"floralcy":0.15,"freshness":0.3833333333333333,"fruityness":0.15,"powderiness":0.15,"spiciness":0.15,"sweetness":0.15,"warmth":0.15,"woodiness":0.15},"core_characteristics":{"density":0.15,"earthiness":0.15,"floralcy":0.5,"freshness":0.15,"fruityness":0.15,"powderiness":0.15,"spiciness":0.15,"sweetness":0.15,"warmth":0.15,"woodiness":0.15},"base_characteristics":{"density":0.32499999999999996,"earthiness":0.5,"floralcy":0.15,"freshness":0.15,"fruityness":0.15,"powderiness":0.15,"spiciness":0.15,"sweetness":0.15,"warmth":0.32499999999999996,"woodiness":0.5}},"shops":[{"shop_name":"Randewoo","domain":"https://randewoo.ru","variants":[{"volume":150,"link":"https://randewoo.ru/product/loewe-pour-homme?source_category=6\u0026preferred=55738","price":14981},{"volume":100,"link":"https://randewoo.ru/product/loewe-pour-homme?source_category=6\u0026preferred=55738","price":11108}]}]},"rank":4,"similarity_score":0.6862077210015376}]}]}